{"meta":{"code":200,"api_version":"2.0.285","issue_date":"20160805"},"result":{"total":1,"hash":"490aca7fa8addf36","items":[{"id":"70000001022482297_ACc4c287G448312323B96G2G5e29d644G6G5G8I2G1I1G3HAfEpy39AI279BG720039AAB94e75Auv067C1C5834C953A8622H0JHd4","region_id":"67","type":"branch","name":"Центр ветеринарии г. Алматы","name_ex":{"primary":"Центр ветеринарии г. Алматы"},"point":{"lon":76.964408,"lat":43.375267},"reg_bc_url":"https:\/\/stat.api.2gis.ru\/?v=2.0&hash=A5cec987G448312323B96G2G5d29d544G6G5G8I2G2I1G3HAfEpy39AI279BG720039AAB94eA53uv067C1C5834C953A8622H0J1G25f","adm_div":[],"address":{"postcode":"050030","components":[{"id":"9430343770561529","type":"street_number","number":"150\/1","street":"Спасская"}],"building_id":"9430047408621051","reg_bc_url":"https:\/\/stat.api.2gis.ru\/?v=2.0&hash=ABc5c487G448312323B96G2G532Ad244G6G5G8I2G2I1G3HAfEpy39AI279BG720039AAB94ed5guv067C1C5834C953A8622H16H0I2gA"},"address_name":"Спасская, 150\/1","org":{"id":"70000001022482296","name":"Центр ветеринарии г. Алматы","branch_count":1},"contact_groups":[{"contacts":[{"type":"phone","value":"+77273855305","text":"+7 (727) 385‒53‒05","reg_bc_url":"https:\/\/stat.api.2gis.ru\/?v=2.0&hash=A9c3c587G448312323B96G2G5c28dg44G6G5G8I2G2I1G3HAfEpy39AI279BG720039AAB94e35Auv067C1C5834C953A8622H2J1G2hA"}]}],"schedule":{"Mon":{"working_hours":[{"to":"18:00","from":"09:00"}]},"Tue":{"working_hours":[{"to":"18:00","from":"09:00"}]},"Wed":{"working_hours":[{"to":"18:00","from":"09:00"}]},"Thu":{"working_hours":[{"to":"18:00","from":"09:00"}]},"Fri":{"working_hours":[{"to":"18:00","from":"09:00"}]}},"rubrics":[{"id":"9429531978891996","short_id":732,"parent_id":"9429531978891265","alias":"otdely_veterinarno_sanitarnogo_kontrolya","name":"Отделы ветеринарно-санитарного контроля","kind":"primary"}],"reviews":{"items":[{"tag":"foursquare","is_reviewable":true}],"org_rating":0,"is_reviewable":false,"org_review_count":0,"is_reviewable_on_flamp":true,"reg_bc_url":"https:\/\/stat.api.2gis.ru\/?v=2.0&hash=A8c8cg87G448312323B96G2G5f26d444G6G5G8I2G2I1G3HAfEpy39AI279BG720039AAB94e45duv067C1C5834C953A8622H13H0I2e2"},"flags":{"photos":false},"external_content":[]}],"filters":{"attributes":[{"label":"Наличный расчет","tag":"general_payment_type_cash","type":"flag"},{"label":"Оплата через банк","tag":"general_payment_type_noncash","type":"flag"}],"rubrics":[{"name":"Отделы ветеринарно-санитарного контроля","id":"9429531978891996","count":1}],"spatial":{"cities":[{"name":"Алматы","id":"9430034490064971","count":1}],"districts":[{"name":"Турксибский","id":"9430021605163013","city_id":"9430034490064971"}]}},"widgets":{"main":[{"labels":{"fri":"Пт","mon":"Пн","now":"Открыто сейчас","sat":"Сб","sun":"ВС","thu":"Чт","tue":"Вт","wed":"Ср","alltime":"Круглосуточно","specified":"В указанное время"},"widget":"worktime","time_format":"24h","first_week_day":"mon"},{"items":[[{"text":"Есть сайт","type":"filter","values":["has_site"]},{"text":"Есть фото","type":"filter","values":["has_photos"]}],[{"text":"Расчёт по картам","type":"filter","values":["general_payment_type_visa","general_payment_type_mastercard"]}]],"widget":"checkboxlist","expanding":[]}],"actions":[{"items":[[{"text":"Открыто","type":"filter","values":["work_time_now"]},{"text":"На карте","type":"filter","values":["bound"]}]],"widget":"checkboxlist","expanding":[]}]},"request_type":"discovery","context_rubrics":[{"id":"9429531978891996","short_id":732,"name":"Отделы ветеринарно-санитарного контроля"}],"search_attributes":{"context_rubrics":["9429531978891996"],"advertisers":[]}}}