{"meta":{"code":200,"api_version":"2.0.286","issue_date":"20160807"},"result":{"total":33,"hash":"b0fbb1953a710af0","items":[{"id":"70000001018096448_g85e9388G448312319A98G2Gcc96c644G6G5G8I2G1I1G4HAfEpy397I3378G7200349954917h2uv08555A19767A68159A4H0JHf7","region_id":"68","type":"branch","name":"Vash-master, сервис-центр","name_ex":{"primary":"Vash-master","extension":"сервис-центр"},"point":{"lon":71.427582,"lat":51.168298},"reg_bc_url":"https:\/\/stat.api.2gis.ru\/?v=2.0&hash=385f9388G448312319A98G2Gc2h3ce44G6G5G8I2G2I1G4HAfEpy397I3378G7200349954916h2uv08555A19767A68159A4H0J1G2fg","adm_div":[],"address":{"components":[{"id":"9571081216069266","type":"street_number","number":"28","street":"Абая проспект"}],"building_id":"9570784863347671","building_code":"Z00P4D9","reg_bc_url":"https:\/\/stat.api.2gis.ru\/?v=2.0&hash=78599d88G448312319A98G2GccB2c544G6G5G8I2G2I1G4HAfEpy397I3378G720034995491dh2uv08555A19767A68159A4H16H0I249"},"address_name":"Абая проспект, 28","address_comment":"1 этаж","org":{"id":"70000001018096447","name":"Vash-master, сервис-центр","branch_count":1},"contact_groups":[{"contacts":[{"type":"phone","value":"+77012231911","text":"+7‒701‒223‒19‒11","reg_bc_url":"https:\/\/stat.api.2gis.ru\/?v=2.0&hash=d85f9e88G448312319A98G2Gc57fc744G6G5G8I2G2I1G4HAfEpy397I3378G720034995491dh2uv08555A19767A68159A4H2J1G243"},{"type":"phone","value":"+77017850031","text":"+7‒701‒785‒00‒31","reg_bc_url":"https:\/\/stat.api.2gis.ru\/?v=2.0&hash=C8549c88G448312319A98G2Gc8egcg44G6G5G8I2G2I1G4HAfEpy397I3378G720034995491ch2uv08555A19767A68159A4H2J1G27e"},{"type":"website","value":"http:\/\/link.2gis.ru\/1.2\/D3AF750A\/online\/20160801\/project68\/70000001018096448\/2gis.ru\/B85c9388G448312319A98G2Gc025cA44G6G5G8I2G2I1G4HAfEpy397I3378G720034995491bh2uv08555A19767A68159A4H4J1G2e9?http:\/\/astana-servis.ru","text":"astana-servis.ru"}]}],"schedule":{"Mon":{"working_hours":[{"to":"20:00","from":"09:00"}]},"Tue":{"working_hours":[{"to":"20:00","from":"09:00"}]},"Wed":{"working_hours":[{"to":"20:00","from":"09:00"}]},"Thu":{"working_hours":[{"to":"20:00","from":"09:00"}]},"Fri":{"working_hours":[{"to":"20:00","from":"09:00"}]},"Sat":{"working_hours":[{"to":"18:00","from":"10:00"}]},"Sun":{"working_hours":[{"to":"18:00","from":"10:00"}]}},"rubrics":[{"id":"9570269467246898","short_id":306,"parent_id":"9570269467246595","alias":"remont_ustanovka_bytovojj_tekhniki","name":"Ремонт \/ установка бытовой техники","kind":"primary"}],"reviews":{"items":[{"tag":"foursquare","is_reviewable":true}],"org_rating":0,"is_reviewable":false,"org_review_count":0,"is_reviewable_on_flamp":true,"reg_bc_url":"https:\/\/stat.api.2gis.ru\/?v=2.0&hash=785d9488G448312319A98G2Gc44ecf44G6G5G8I2G2I1G4HAfEpy397I3378G7200349954913h2uv08555A19767A68159A4H13H0I26b"},"ads":{"text":"Мастера с выездом на дом.","article":"Наши мастера быстро и оперативно прибудут на место в назначенное Вами время, точно диагностируют проблему с использованием современного оборудования и устранят ее в кратчайшие сроки. <br \/>Ремонт и диагностика:<br \/>- электрической плиты<br \/>- Стиральных машин автомат<br \/>- керамических и стеклокерамических поверхностей<br \/>- духовых шкафов (духовок)<br \/>- кухонных вытяжек<br \/>- посудомоечной машины<br \/>- газовых плит<br \/>Ремонт осуществляется у Вас на дому, все ремонтные работы,<br \/>а также работы по замене деталей производятся также у Вас дома.<br \/>Вы не тратите деньги и время на вывоз техники, повторную установку<br \/>&ndash; мы работаем аккуратно, слаженно и быстро.<br \/>Наши мастера обладают обширными знаниями и большим опытом, <br \/>поэтому ремонт бытовой техники не займет много времени, будет выполнен качественно, профессионально и грамотно.","options":{"logo":{"use_default_value":true}}},"flags":{"photos":false},"external_content":[]},{"id":"70000001019141212_385d9f88G44831231AA98G2Gce79cg44G6G5G8I2G1I2G3HAfEpy397I3378G720034995491Ah2uv08555A24244468159A2H0JH8f","region_id":"68","type":"branch","name":"LG, сервисный центр","name_ex":{"primary":"LG","extension":"сервисный центр"},"point":{"lon":71.440849,"lat":51.166557},"reg_bc_url":"https:\/\/stat.api.2gis.ru\/?v=2.0&hash=h85c9488G44831231AA98G2Gc56fce44G6G5G8I2G2I2G3HAfEpy397I3378G720034995491fh2uv08555A24244468159A2H0J1G2d7","adm_div":[],"address":{"components":[{"id":"9571081216087196","type":"street_number","number":"52","street":"Кенесары"}],"building_id":"9570784863339368","building_code":"Z00Y7D0","reg_bc_url":"https:\/\/stat.api.2gis.ru\/?v=2.0&hash=985b9988G44831231AA98G2GcfAgcg44G6G5G8I2G2I2G3HAfEpy397I3378G7200349954912h2uv08555A24244468159A2H16H0I25d"},"address_name":"Кенесары, 52","address_comment":"1 этаж","org":{"id":"70000001019141211","name":"LG, сервисный центр","branch_count":1},"contact_groups":[{"contacts":[{"type":"phone","value":"88000805805","text":"8‒800‒080‒58‒05","comment":"бесплатная единая справочная","reg_bc_url":"https:\/\/stat.api.2gis.ru\/?v=2.0&hash=385b9988G44831231AA98G2Gcf28ce44G6G5G8I2G2I2G3HAfEpy397I3378G720034995491ch2uv08555A24244468159A2H2J1G277"},{"type":"phone","value":"2255","text":"22‒55","comment":"бесплатная единая справочная","reg_bc_url":"https:\/\/stat.api.2gis.ru\/?v=2.0&hash=785c9f88G44831231AA98G2Gc03dc644G6G5G8I2G2I2G3HAfEpy397I3378G720034995491fh2uv08555A24244468159A2H2J1G264"},{"type":"website","value":"http:\/\/link.2gis.ru\/1.2\/40A592CA\/online\/20160801\/project68\/70000001019141212\/2gis.ru\/485e9988G44831231AA98G2Gcdgdc544G6G5G8I2G2I2G3HAfEpy397I3378G7200349954917h2uv08555A24244468159A2H4J1G277?http:\/\/www.lg.com","text":"www.lg.com"},{"type":"vkontakte","value":"https:\/\/vk.com\/lg_electronics_kazakhstan","text":"https:\/\/vk.com\/lg_electronics_kazakhstan","reg_bc_url":"https:\/\/stat.api.2gis.ru\/?v=2.0&hash=e8589f88G44831231AA98G2Gcf3dc244G6G5G8I2G2I2G3HAfEpy397I3378G7200349954915h2uv08555A24244468159A2H23H0I22c"},{"type":"twitter","value":"https:\/\/twitter.com\/@lgelectronicskz","text":"https:\/\/twitter.com\/@lgelectronicskz","reg_bc_url":"https:\/\/stat.api.2gis.ru\/?v=2.0&hash=58529f88G44831231AA98G2Gc0h3c244G6G5G8I2G2I2G3HAfEpy397I3378G7200349954911h2uv08555A24244468159A2H23H0I256"},{"type":"facebook","value":"https:\/\/facebook.com\/LGEKazakhstan","text":"https:\/\/facebook.com\/LGEKazakhstan","reg_bc_url":"https:\/\/stat.api.2gis.ru\/?v=2.0&hash=i8559f88G44831231AA98G2Gc485cg44G6G5G8I2G2I2G3HAfEpy397I3378G7200349954916h2uv08555A24244468159A2H23H0I258"},{"type":"instagram","value":"https:\/\/instagram.com\/lg_electronics_kz","text":"https:\/\/instagram.com\/lg_electronics_kz","reg_bc_url":"https:\/\/stat.api.2gis.ru\/?v=2.0&hash=78539788G44831231AA98G2Gc5AdcA44G6G5G8I2G2I2G3HAfEpy397I3378G720034995491fh2uv08555A24244468159A2H23H0I21c"}]}],"schedule":{"Mon":{"working_hours":[{"to":"14:00","from":"10:00"},{"to":"19:00","from":"15:00"}]},"Tue":{"working_hours":[{"to":"14:00","from":"10:00"},{"to":"19:00","from":"15:00"}]},"Wed":{"working_hours":[{"to":"14:00","from":"10:00"},{"to":"19:00","from":"15:00"}]},"Thu":{"working_hours":[{"to":"14:00","from":"10:00"},{"to":"19:00","from":"15:00"}]},"Fri":{"working_hours":[{"to":"14:00","from":"10:00"},{"to":"19:00","from":"15:00"}]},"Sat":{"working_hours":[{"to":"14:00","from":"10:00"}]}},"rubrics":[{"id":"9570269467246898","short_id":306,"parent_id":"9570269467246595","alias":"remont_ustanovka_bytovojj_tekhniki","name":"Ремонт \/ установка бытовой техники","kind":"primary"}],"reviews":{"items":[{"tag":"foursquare","is_reviewable":true}],"org_rating":0,"is_reviewable":false,"org_review_count":0,"is_reviewable_on_flamp":true,"reg_bc_url":"https:\/\/stat.api.2gis.ru\/?v=2.0&hash=B85e9e88G44831231AA98G2Gc4g3ce44G6G5G8I2G2I2G3HAfEpy397I3378G720034995491Ah2uv08555A24244468159A2H13H0I2f3"},"flags":{"photos":false},"external_content":[]},{"id":"70000001018109955_C8539388G448312319A98G2Gc856c744G6G5G8I2G1I3G3HAfEpy397I3378G7200349954913h2uv08555A20AB8768159A2H0JH15","region_id":"68","type":"branch","name":"Аскон 7, сервис-центр","name_ex":{"primary":"Аскон 7","extension":"сервис-центр"},"point":{"lon":71.442077,"lat":51.164778},"reg_bc_url":"https:\/\/stat.api.2gis.ru\/?v=2.0&hash=B8569288G448312319A98G2Gc133c644G6G5G8I2G2I3G3HAfEpy397I3378G720034995491Ah2uv08555A20AB8768159A2H0J1G2f6","adm_div":[],"address":{"components":[{"id":"9571081216069239","type":"street_number","number":"19","street":"Иманова"}],"building_id":"9570784863350724","reg_bc_url":"https:\/\/stat.api.2gis.ru\/?v=2.0&hash=685b9f88G448312319A98G2GcaeAc944G6G5G8I2G2I3G3HAfEpy397I3378G720034995491ch2uv08555A20AB8768159A2H16H0I2d6"},"address_name":"Иманова, 19","address_comment":"цокольный этаж","org":{"id":"70000001018109954","name":"Аскон 7, сервис-центр","branch_count":1},"contact_groups":[{"contacts":[{"type":"phone","value":"+77015200729","text":"+7‒701‒520‒07‒29","reg_bc_url":"https:\/\/stat.api.2gis.ru\/?v=2.0&hash=78579988G448312319A98G2Gc773c344G6G5G8I2G2I3G3HAfEpy397I3378G7200349954918h2uv08555A20AB8768159A2H2J1G2e6"},{"type":"phone","value":"+77172217345","text":"+7 (7172) 21‒73‒45","reg_bc_url":"https:\/\/stat.api.2gis.ru\/?v=2.0&hash=785c9488G448312319A98G2Gc1Bgce44G6G5G8I2G2I3G3HAfEpy397I3378G7200349954914h2uv08555A20AB8768159A2H2J1G295"},{"type":"phone","value":"+77172215216","text":"+7 (7172) 21‒52‒16","reg_bc_url":"https:\/\/stat.api.2gis.ru\/?v=2.0&hash=A85g9188G448312319A98G2Gcae4c944G6G5G8I2G2I3G3HAfEpy397I3378G7200349954919h2uv08555A20AB8768159A2H2J1G275"},{"type":"website","value":"http:\/\/link.2gis.ru\/1.2\/46A64776\/online\/20160801\/project68\/70000001018109955\/2gis.ru\/C85c9388G448312319A98G2Gcc3hc444G6G5G8I2G2I3G3HAfEpy397I3378G7200349954916h2uv08555A20AB8768159A2H4J1G2A3?http:\/\/askon7.kz","text":"askon7.kz"}]}],"schedule":{"Mon":{"working_hours":[{"to":"13:00","from":"09:00"},{"to":"18:00","from":"14:00"}]},"Tue":{"working_hours":[{"to":"13:00","from":"09:00"},{"to":"18:00","from":"14:00"}]},"Wed":{"working_hours":[{"to":"13:00","from":"09:00"},{"to":"18:00","from":"14:00"}]},"Thu":{"working_hours":[{"to":"13:00","from":"09:00"},{"to":"18:00","from":"14:00"}]},"Fri":{"working_hours":[{"to":"13:00","from":"09:00"},{"to":"18:00","from":"14:00"}]},"Sat":{"working_hours":[{"to":"13:00","from":"09:00"}]}},"rubrics":[{"id":"9570269467246898","short_id":306,"parent_id":"9570269467246595","alias":"remont_ustanovka_bytovojj_tekhniki","name":"Ремонт \/ установка бытовой техники","kind":"primary"}],"reviews":{"items":[{"tag":"foursquare","is_reviewable":true}],"org_rating":0,"is_reviewable":false,"org_review_count":0,"is_reviewable_on_flamp":true,"reg_bc_url":"https:\/\/stat.api.2gis.ru\/?v=2.0&hash=785d9188G448312319A98G2Gc028cd44G6G5G8I2G2I3G3HAfEpy397I3378G720034995491eh2uv08555A20AB8768159A2H13H0I2Ae"},"flags":{"photos":false},"external_content":[]},{"id":"70000001018093144_d8599488G448312319A98G2GcbA8c244G6G5G8I2G1I4G3HAfEpy397I3378G7200349954914h2uv08555A19437668159A2H0JH76","region_id":"68","type":"branch","name":"Мечта-Сервис, ТОО, сервисный центр","name_ex":{"primary":"Мечта-Сервис, ТОО","extension":"сервисный центр"},"point":{"lon":71.392288,"lat":51.179441},"reg_bc_url":"https:\/\/stat.api.2gis.ru\/?v=2.0&hash=68549588G448312319A98G2Gcc8hc444G6G5G8I2G2I4G3HAfEpy397I3378G720034995491dh2uv08555A19437668159A2H0J1G2h3","adm_div":[],"address":{"components":[{"id":"9571081216070933","type":"street_number","number":"6","street":"Московская"}],"building_id":"9570784863328037","reg_bc_url":"https:\/\/stat.api.2gis.ru\/?v=2.0&hash=C8569g88G448312319A98G2Gc08BcA44G6G5G8I2G2I4G3HAfEpy397I3378G7200349954911h2uv08555A19437668159A2H16H0I23f"},"address_name":"Московская, 6","org":{"id":"70000001018093143","name":"Мечта-Сервис, ТОО, сервисный центр","branch_count":1},"contact_groups":[{"contacts":[{"type":"phone","value":"+77778824084","text":"+7‒777‒882‒40‒84","reg_bc_url":"https:\/\/stat.api.2gis.ru\/?v=2.0&hash=A85c9988G448312319A98G2Gcbfgce44G6G5G8I2G2I4G3HAfEpy397I3378G720034995491fh2uv08555A19437668159A2H2J1G24f"},{"type":"phone","value":"+77172383479","text":"+7 (7172) 38‒34‒79","reg_bc_url":"https:\/\/stat.api.2gis.ru\/?v=2.0&hash=48569b88G448312319A98G2Gc7e3cf44G6G5G8I2G2I4G3HAfEpy397I3378G7200349954913h2uv08555A19437668159A2H2J1G28e"},{"type":"phone","value":"+77172383754","text":"+7 (7172) 38‒37‒54","reg_bc_url":"https:\/\/stat.api.2gis.ru\/?v=2.0&hash=f8599888G448312319A98G2Gc4f3c644G6G5G8I2G2I4G3HAfEpy397I3378G720034995491bh2uv08555A19437668159A2H2J1G26A"},{"type":"website","value":"http:\/\/link.2gis.ru\/1.2\/4A8E06BD\/online\/20160801\/project68\/70000001018093144\/2gis.ru\/685f9g88G448312319A98G2GcbAecg44G6G5G8I2G2I4G3HAfEpy397I3378G7200349954913h2uv08555A19437668159A2H4J1G2A1?http:\/\/ms-ast.kz","text":"ms-ast.kz"}]}],"schedule":{"Mon":{"working_hours":[{"to":"18:00","from":"09:00"}]},"Tue":{"working_hours":[{"to":"18:00","from":"09:00"}]},"Wed":{"working_hours":[{"to":"18:00","from":"09:00"}]},"Thu":{"working_hours":[{"to":"18:00","from":"09:00"}]},"Fri":{"working_hours":[{"to":"18:00","from":"09:00"}]},"Sat":{"working_hours":[{"to":"13:00","from":"09:00"}]}},"rubrics":[{"id":"9570269467246898","short_id":306,"parent_id":"9570269467246595","alias":"remont_ustanovka_bytovojj_tekhniki","name":"Ремонт \/ установка бытовой техники","kind":"primary"},{"id":"9570269467271404","short_id":24812,"parent_id":"9570269467246607","alias":"remont_obsluzhivanie_klimaticheskogo_oborudovaniya","name":"Ремонт \/ обслуживание климатического оборудования","kind":"primary"},{"id":"9570269467247242","short_id":650,"parent_id":"9570269467246595","alias":"remont_kompyuterov","name":"Ремонт компьютеров","kind":"additional"},{"id":"9570269467247553","short_id":961,"parent_id":"9570269467246595","alias":"remont_audio_video_cifrovojj_tekhniki","name":"Ремонт аудио \/ видео \/ цифровой техники","kind":"additional"}],"reviews":{"items":[{"tag":"foursquare","is_reviewable":true}],"org_rating":0,"is_reviewable":false,"org_review_count":0,"is_reviewable_on_flamp":true,"reg_bc_url":"https:\/\/stat.api.2gis.ru\/?v=2.0&hash=i8579588G448312319A98G2GceAAc444G6G5G8I2G2I4G3HAfEpy397I3378G720034995491gh2uv08555A19437668159A2H13H0I2gb"},"flags":{"photos":false},"external_content":[]},{"id":"70000001021657368_985b9988G448312322A98G2Gc5A6cd44G6G5G8I2G1I5G3HAfEpy397I3378G7200349954912h2uv08555A75859A68159A2H0JHf5","region_id":"68","type":"branch","name":"PHOTOMASTER, ИП","name_ex":{"primary":"PHOTOMASTER, ИП"},"point":{"lon":71.473198,"lat":51.151235},"reg_bc_url":"https:\/\/stat.api.2gis.ru\/?v=2.0&hash=B8599d88G448312322A98G2Gccd7c944G6G5G8I2G2I5G3HAfEpy397I3378G7200349954917h2uv08555A75859A68159A2H0J1G2Ag","adm_div":[{"id":"9570810633125902","name":"4-й м-н","type":"living_area"}],"address":{"components":[{"id":"9571081216068862","type":"street_number","number":"9","street":"Жирентаева"}],"building_id":"9570784863327490","reg_bc_url":"https:\/\/stat.api.2gis.ru\/?v=2.0&hash=g8599788G448312322A98G2Gc923c344G6G5G8I2G2I5G3HAfEpy397I3378G7200349954916h2uv08555A75859A68159A2H16H0I23d"},"address_name":"Жирентаева, 9","address_comment":"Шамшая","org":{"id":"70000001021657367","name":"PHOTOMASTER, ИП","branch_count":1},"contact_groups":[{"contacts":[{"type":"phone","value":"+77076663047","text":"+7‒707‒666‒30‒47","reg_bc_url":"https:\/\/stat.api.2gis.ru\/?v=2.0&hash=i8569788G448312322A98G2Gc8h8cd44G6G5G8I2G2I5G3HAfEpy397I3378G7200349954916h2uv08555A75859A68159A2H2J1G271"}]}],"schedule":{"Mon":{"working_hours":[{"to":"19:00","from":"11:00"}]},"Tue":{"working_hours":[{"to":"19:00","from":"11:00"}]},"Wed":{"working_hours":[{"to":"19:00","from":"11:00"}]},"Thu":{"working_hours":[{"to":"19:00","from":"11:00"}]},"Fri":{"working_hours":[{"to":"19:00","from":"11:00"}]},"Sat":{"working_hours":[{"to":"19:00","from":"11:00"}]}},"rubrics":[{"id":"9570269467247553","short_id":961,"parent_id":"9570269467246595","alias":"remont_audio_video_cifrovojj_tekhniki","name":"Ремонт аудио \/ видео \/ цифровой техники","kind":"primary"},{"id":"9570269467247242","short_id":650,"parent_id":"9570269467246595","alias":"remont_kompyuterov","name":"Ремонт компьютеров","kind":"primary"},{"id":"9570269467247220","short_id":628,"parent_id":"9570269467246595","alias":"remont_orgtekhniki","name":"Ремонт оргтехники","kind":"additional"},{"id":"9570269467246898","short_id":306,"parent_id":"9570269467246595","alias":"remont_ustanovka_bytovojj_tekhniki","name":"Ремонт \/ установка бытовой техники","kind":"additional"}],"reviews":{"items":[{"tag":"foursquare","is_reviewable":true}],"org_rating":0,"is_reviewable":false,"org_review_count":0,"is_reviewable_on_flamp":true,"reg_bc_url":"https:\/\/stat.api.2gis.ru\/?v=2.0&hash=i8569b88G448312322A98G2Gc1Bcc744G6G5G8I2G2I5G3HAfEpy397I3378G7200349954919h2uv08555A75859A68159A2H13H0I2f8"},"flags":{"photos":true},"external_content":[{"type":"photo_album","count":1,"subtype":"common","reg_bc_url":"https:\/\/stat.api.2gis.ru\/?v=2.0&hash=88599f88G448312322A98G2Gc17ec644G6G5G8I2G2I5G3HAfEpy397I3378G7200349954913h2uv08555A75859A68159A2H1BH0I2gb","main_photo_url":"https:\/\/i8.photo.2gis.com\/main\/branch\/68\/70000001021657368\/common"}]},{"id":"70000001020084421_h8549b88G448312321A98G2Gc7d6cA44G6G5G8I2G1I6G3HAfEpy397I3378G7200349954913h2uv08555A18565368159A2H0JH5e","region_id":"68","type":"branch","name":"Home Service, центр ремонта бытовой техники","name_ex":{"primary":"Home Service","extension":"центр ремонта бытовой техники"},"point":{"lon":71.412163,"lat":51.163698},"reg_bc_url":"https:\/\/stat.api.2gis.ru\/?v=2.0&hash=g8599588G448312321A98G2Gc5Bhc944G6G5G8I2G2I6G3HAfEpy397I3378G7200349954914h2uv08555A18565368159A2H0J1G2c1","adm_div":[],"address":{"components":[{"id":"9571081216068637","type":"street_number","number":"19","street":"Кенесары"}],"building_id":"9570784863348098","building_code":"Z10P5X9","reg_bc_url":"https:\/\/stat.api.2gis.ru\/?v=2.0&hash=h85d9388G448312321A98G2Gc034cf44G6G5G8I2G2I6G3HAfEpy397I3378G7200349954911h2uv08555A18565368159A2H16H0I2de"},"address_name":"Кенесары, 19","address_comment":"1 этаж; вход с торца","org":{"id":"70000001020084420","name":"Home Service, центр ремонта бытовой техники","branch_count":1},"contact_groups":[{"contacts":[{"type":"phone","value":"+77172230029","text":"+7 (7172) 23‒00‒29","reg_bc_url":"https:\/\/stat.api.2gis.ru\/?v=2.0&hash=585c9A88G448312321A98G2Gcb5ecd44G6G5G8I2G2I6G3HAfEpy397I3378G7200349954913h2uv08555A18565368159A2H2J1G291"},{"type":"phone","value":"+77789006577","text":"+7‒778‒900‒65‒77","reg_bc_url":"https:\/\/stat.api.2gis.ru\/?v=2.0&hash=f8529A88G448312321A98G2Gcc38cd44G6G5G8I2G2I6G3HAfEpy397I3378G720034995491bh2uv08555A18565368159A2H2J1G29e"},{"type":"phone","value":"+77172266401","text":"+7 (7172) 26‒64‒01","reg_bc_url":"https:\/\/stat.api.2gis.ru\/?v=2.0&hash=i85e9488G448312321A98G2Gc5dAc444G6G5G8I2G2I6G3HAfEpy397I3378G720034995491fh2uv08555A18565368159A2H2J1G2g6"},{"type":"website","value":"http:\/\/link.2gis.ru\/1.2\/84CD9D21\/online\/20160801\/project68\/70000001020084421\/2gis.ru\/C8519g88G448312321A98G2GcdB2c644G6G5G8I2G2I6G3HAfEpy397I3378G7200349954913h2uv08555A18565368159A2H4J1G2Bg?http:\/\/remont-ast.kz","text":"remont-ast.kz"}]}],"schedule":{"Mon":{"working_hours":[{"to":"13:00","from":"09:00"},{"to":"18:00","from":"14:00"}]},"Tue":{"working_hours":[{"to":"13:00","from":"09:00"},{"to":"18:00","from":"14:00"}]},"Wed":{"working_hours":[{"to":"13:00","from":"09:00"},{"to":"20:00","from":"14:00"}]},"Thu":{"working_hours":[{"to":"13:00","from":"09:00"},{"to":"20:00","from":"14:00"}]},"Fri":{"working_hours":[{"to":"13:00","from":"09:00"},{"to":"20:00","from":"14:00"}]},"Sat":{"working_hours":[{"to":"13:00","from":"09:00"},{"to":"18:00","from":"14:00"}]},"Sun":{"working_hours":[{"to":"13:00","from":"09:00"},{"to":"18:00","from":"14:00"}]}},"rubrics":[{"id":"9570269467246898","short_id":306,"parent_id":"9570269467246595","alias":"remont_ustanovka_bytovojj_tekhniki","name":"Ремонт \/ установка бытовой техники","kind":"primary"}],"reviews":{"items":[{"tag":"foursquare","is_reviewable":true}],"org_rating":0,"is_reviewable":false,"org_review_count":0,"is_reviewable_on_flamp":true,"reg_bc_url":"https:\/\/stat.api.2gis.ru\/?v=2.0&hash=385f9788G448312321A98G2Gc8f3c144G6G5G8I2G2I6G3HAfEpy397I3378G7200349954913h2uv08555A18565368159A2H13H0I23c"},"flags":{"photos":false},"external_content":[]},{"id":"70000001018515757_A8579288G448312319A98G2Gc22fcf44G6G5G8I2G1I7G3HAfEpy397I3378G7200349954912h2uv08555A61698968159A2H0JHcB","region_id":"68","type":"branch","name":"Империя сервисных услуг, ТОО","name_ex":{"primary":"Империя сервисных услуг, ТОО"},"point":{"lon":71.40427,"lat":51.174205},"reg_bc_url":"https:\/\/stat.api.2gis.ru\/?v=2.0&hash=g8589588G448312319A98G2Gc82Ac344G6G5G8I2G2I7G3HAfEpy397I3378G7200349954915h2uv08555A61698968159A2H0J1G277","adm_div":[],"address":{"components":[{"id":"9571081216087724","type":"street_number","number":"26\/2","street":"Богенбай батыра проспект"}],"building_id":"9570784863323610","reg_bc_url":"https:\/\/stat.api.2gis.ru\/?v=2.0&hash=i8519A88G448312319A98G2Gc4fAcf44G6G5G8I2G2I7G3HAfEpy397I3378G720034995491fh2uv08555A61698968159A2H16H0I287"},"address_name":"Богенбай батыра проспект, 26\/2","address_comment":"9 офис; 3 этаж","org":{"id":"70000001018515756","name":"Империя сервисных услуг, ТОО","branch_count":1},"contact_groups":[{"contacts":[{"type":"phone","value":"+77172477377","text":"+7 (7172) 47‒73‒77","reg_bc_url":"https:\/\/stat.api.2gis.ru\/?v=2.0&hash=78539488G448312319A98G2Gc8e6c344G6G5G8I2G2I7G3HAfEpy397I3378G720034995491Ah2uv08555A61698968159A2H2J1G268"},{"type":"phone","value":"+77079477377","text":"+7‒707‒947‒73‒77","reg_bc_url":"https:\/\/stat.api.2gis.ru\/?v=2.0&hash=58589888G448312319A98G2Gc696cd44G6G5G8I2G2I7G3HAfEpy397I3378G720034995491dh2uv08555A61698968159A2H2J1G2A5"},{"type":"website","value":"http:\/\/link.2gis.ru\/1.2\/4A031AC9\/online\/20160801\/project68\/70000001018515757\/2gis.ru\/h8529c88G448312319A98G2Gc37cc844G6G5G8I2G2I7G3HAfEpy397I3378G720034995491eh2uv08555A61698968159A2H4J1G2B8?http:\/\/isu.kz","text":"isu.kz"},{"type":"vkontakte","value":"https:\/\/vk.com\/isu_kz","text":"https:\/\/vk.com\/isu_kz","reg_bc_url":"https:\/\/stat.api.2gis.ru\/?v=2.0&hash=B8549788G448312319A98G2Gc257cc44G6G5G8I2G2I7G3HAfEpy397I3378G720034995491bh2uv08555A61698968159A2H23H0I2gg"},{"type":"facebook","value":"https:\/\/facebook.com\/isucompany","text":"https:\/\/facebook.com\/isucompany","reg_bc_url":"https:\/\/stat.api.2gis.ru\/?v=2.0&hash=B8589g88G448312319A98G2GcbgAc544G6G5G8I2G2I7G3HAfEpy397I3378G7200349954914h2uv08555A61698968159A2H23H0I2e7"},{"type":"instagram","value":"https:\/\/instagram.com\/isu.kz","text":"https:\/\/instagram.com\/isu.kz","reg_bc_url":"https:\/\/stat.api.2gis.ru\/?v=2.0&hash=985f9f88G448312319A98G2Gcf6gc444G6G5G8I2G2I7G3HAfEpy397I3378G7200349954914h2uv08555A61698968159A2H23H0I22d"}]}],"schedule":{"Mon":{"working_hours":[{"to":"21:00","from":"09:00"}]},"Tue":{"working_hours":[{"to":"21:00","from":"09:00"}]},"Wed":{"working_hours":[{"to":"21:00","from":"09:00"}]},"Thu":{"working_hours":[{"to":"21:00","from":"09:00"}]},"Fri":{"working_hours":[{"to":"21:00","from":"09:00"}]},"Sat":{"working_hours":[{"to":"21:00","from":"09:00"}]},"Sun":{"working_hours":[{"to":"21:00","from":"09:00"}]}},"rubrics":[{"id":"9570269467350789","short_id":104197,"parent_id":"9570269467246601","alias":"remont_ustanovka_santekhnicheskogo_oborudovaniya","name":"Ремонт \/ установка сантехнического оборудования","kind":"primary"},{"id":"9570269467246898","short_id":306,"parent_id":"9570269467246595","alias":"remont_ustanovka_bytovojj_tekhniki","name":"Ремонт \/ установка бытовой техники","kind":"primary"},{"id":"9570269467356908","short_id":110316,"parent_id":"9570269467289495","alias":"vyezdnaya_tekhnicheskaya_pomoshh_na_doroge","name":"Выездная техническая помощь на дороге","kind":"primary"},{"id":"9570269467297458","short_id":50866,"parent_id":"9570269467246602","alias":"vskrytie_obsluzhivanie_zamkov_dverejj","name":"Вскрытие \/ обслуживание замков, дверей","kind":"primary"},{"id":"9570269467247301","short_id":709,"parent_id":"9570269467246602","alias":"professionalnaya_uborka","name":"Профессиональная уборка","kind":"primary"}],"reviews":{"items":[{"tag":"foursquare","is_reviewable":true}],"org_rating":0,"is_reviewable":false,"org_review_count":0,"is_reviewable_on_flamp":true,"reg_bc_url":"https:\/\/stat.api.2gis.ru\/?v=2.0&hash=38549488G448312319A98G2Gc0ffc244G6G5G8I2G2I7G3HAfEpy397I3378G720034995491eh2uv08555A61698968159A2H13H0I2dA"},"flags":{"photos":false},"external_content":[]},{"id":"70000001018114516_e8529e88G448312319A98G2Gcb7BcA44G6G5G8I2G1I8G3HAfEpy397I3378G7200349954919h2uv08555A21574868159A2H0JH47","region_id":"68","type":"branch","name":"Жана Жулдыз, сервисный центр","name_ex":{"primary":"Жана Жулдыз","extension":"сервисный центр"},"point":{"lon":71.385675,"lat":51.168768},"reg_bc_url":"https:\/\/stat.api.2gis.ru\/?v=2.0&hash=58559d88G448312319A98G2Gcfddcg44G6G5G8I2G2I8G3HAfEpy397I3378G7200349954914h2uv08555A21574868159A2H0J1G2A9","adm_div":[],"address":{"components":[{"id":"9571081216070540","type":"street_number","number":"13\/1","street":"Косшыгулулы"}],"building_id":"9570784863339325","building_code":"Z10K1A3","reg_bc_url":"https:\/\/stat.api.2gis.ru\/?v=2.0&hash=f8579388G448312319A98G2GcfgAce44G6G5G8I2G2I8G3HAfEpy397I3378G7200349954919h2uv08555A21574868159A2H16H0I273"},"address_name":"Косшыгулулы, 13\/1","address_comment":"1 помещение","org":{"id":"70000001018114515","name":"Жана Жулдыз, сервисный центр","branch_count":1},"contact_groups":[{"contacts":[{"type":"phone","value":"+77172305666","text":"+7 (7172) 30‒56‒66","reg_bc_url":"https:\/\/stat.api.2gis.ru\/?v=2.0&hash=h85c9388G448312319A98G2Gc3d8c944G6G5G8I2G2I8G3HAfEpy397I3378G720034995491bh2uv08555A21574868159A2H2J1G2h6"},{"type":"phone","value":"+77172305656","text":"+7 (7172) 30‒56‒56","reg_bc_url":"https:\/\/stat.api.2gis.ru\/?v=2.0&hash=485f9288G448312319A98G2Gc9dec144G6G5G8I2G2I8G3HAfEpy397I3378G7200349954919h2uv08555A21574868159A2H2J1G23f"},{"type":"phone","value":"+77082599770","text":"+7‒708‒259‒97‒70","reg_bc_url":"https:\/\/stat.api.2gis.ru\/?v=2.0&hash=g8549A88G448312319A98G2Gcbchce44G6G5G8I2G2I8G3HAfEpy397I3378G720034995491bh2uv08555A21574868159A2H2J1G24b"}]}],"schedule":{"Mon":{"working_hours":[{"to":"19:00","from":"10:00"}]},"Tue":{"working_hours":[{"to":"19:00","from":"10:00"}]},"Wed":{"working_hours":[{"to":"19:00","from":"10:00"}]},"Thu":{"working_hours":[{"to":"19:00","from":"10:00"}]},"Fri":{"working_hours":[{"to":"19:00","from":"10:00"}]},"Sat":{"working_hours":[{"to":"15:00","from":"10:00"}]},"Sun":{"working_hours":[{"to":"15:00","from":"10:00"}]}},"rubrics":[{"id":"9570269467246898","short_id":306,"parent_id":"9570269467246595","alias":"remont_ustanovka_bytovojj_tekhniki","name":"Ремонт \/ установка бытовой техники","kind":"primary"},{"id":"9570269467247242","short_id":650,"parent_id":"9570269467246595","alias":"remont_kompyuterov","name":"Ремонт компьютеров","kind":"primary"}],"reviews":{"items":[{"tag":"foursquare","is_reviewable":true}],"org_rating":0,"is_reviewable":false,"org_review_count":0,"is_reviewable_on_flamp":true,"reg_bc_url":"https:\/\/stat.api.2gis.ru\/?v=2.0&hash=78559188G448312319A98G2Gca68c844G6G5G8I2G2I8G3HAfEpy397I3378G7200349954911h2uv08555A21574868159A2H13H0I22e"},"flags":{"photos":false},"external_content":[]},{"id":"70000001018120981_58599288G448312319A98G2Gc14hcA44G6G5G8I2G1I9G3HAfEpy397I3378G7200349954919h2uv08555A221BB368159A2H0JH84","region_id":"68","type":"branch","name":"Қолқанат-Сервис, ТОО, сервисный центр","name_ex":{"primary":"Қолқанат-Сервис, ТОО","extension":"сервисный центр"},"point":{"lon":71.470396,"lat":51.143154},"reg_bc_url":"https:\/\/stat.api.2gis.ru\/?v=2.0&hash=C8549888G448312319A98G2Gcb3dcd44G6G5G8I2G2I9G3HAfEpy397I3378G7200349954914h2uv08555A221BB368159A2H0J1G2A1","adm_div":[{"id":"9570810633125905","name":"Текстильщиков м-н","type":"living_area"}],"address":{"components":[{"id":"9571081216068591","type":"street_number","number":"10","street":"Майлина"}],"building_id":"9570784863327635","reg_bc_url":"https:\/\/stat.api.2gis.ru\/?v=2.0&hash=C8579688G448312319A98G2Gcb4dc344G6G5G8I2G2I9G3HAfEpy397I3378G720034995491eh2uv08555A221BB368159A2H16H0I2de"},"address_name":"Майлина, 10","address_comment":"100 офис; 1 этаж","org":{"id":"70000001018120980","name":"Қолқанат-Сервис, ТОО, сервисный центр","branch_count":1},"contact_groups":[{"contacts":[{"type":"phone","value":"+77172780604","text":"+7 (7172) 78‒06‒04","reg_bc_url":"https:\/\/stat.api.2gis.ru\/?v=2.0&hash=g8579f88G448312319A98G2Gc7Bfce44G6G5G8I2G2I9G3HAfEpy397I3378G720034995491bh2uv08555A221BB368159A2H2J1G268"},{"type":"phone","value":"+77172627434","text":"+7 (7172) 62‒74‒34","reg_bc_url":"https:\/\/stat.api.2gis.ru\/?v=2.0&hash=885A9c88G448312319A98G2Gc8B5cA44G6G5G8I2G2I9G3HAfEpy397I3378G7200349954914h2uv08555A221BB368159A2H2J1G244"},{"type":"phone","value":"+77027349500","text":"+7‒702‒734‒95‒00","reg_bc_url":"https:\/\/stat.api.2gis.ru\/?v=2.0&hash=e8589g88G448312319A98G2GcdA2cg44G6G5G8I2G2I9G3HAfEpy397I3378G720034995491Ah2uv08555A221BB368159A2H2J1G2h4"},{"type":"website","value":"http:\/\/link.2gis.ru\/1.2\/71390CC3\/online\/20160801\/project68\/70000001018120981\/2gis.ru\/78549388G448312319A98G2Gce72c844G6G5G8I2G2I9G3HAfEpy397I3378G720034995491dh2uv08555A221BB368159A2H4J1G283?http:\/\/kolkanat-service.kz","text":"kolkanat-service.kz"},{"type":"website","value":"http:\/\/link.2gis.ru\/1.2\/5D661A17\/online\/20160801\/project68\/70000001018120981\/2gis.ru\/68539388G448312319A98G2Gce39cf44G6G5G8I2G2I9G3HAfEpy397I3378G720034995491fh2uv08555A221BB368159A2H4J1G289?http:\/\/ok.ru\/profile\/572492458962","text":"ok.ru\/profile\/572492458962"},{"type":"vkontakte","value":"https:\/\/vk.com\/kolkanat_service","text":"https:\/\/vk.com\/kolkanat_service","reg_bc_url":"https:\/\/stat.api.2gis.ru\/?v=2.0&hash=i8549d88G448312319A98G2GcbfBc344G6G5G8I2G2I9G3HAfEpy397I3378G7200349954917h2uv08555A221BB368159A2H23H0I28d"},{"type":"instagram","value":"https:\/\/instagram.com\/kolkanatservice","text":"https:\/\/instagram.com\/kolkanatservice","reg_bc_url":"https:\/\/stat.api.2gis.ru\/?v=2.0&hash=585b9788G448312319A98G2Gcc3Ac244G6G5G8I2G2I9G3HAfEpy397I3378G720034995491ch2uv08555A221BB368159A2H23H0I2d4"}]}],"schedule":{"Mon":{"working_hours":[{"to":"19:00","from":"09:00"}]},"Tue":{"working_hours":[{"to":"19:00","from":"09:00"}]},"Wed":{"working_hours":[{"to":"19:00","from":"09:00"}]},"Thu":{"working_hours":[{"to":"19:00","from":"09:00"}]},"Fri":{"working_hours":[{"to":"19:00","from":"09:00"}]},"Sat":{"working_hours":[{"to":"19:00","from":"09:00"}]}},"rubrics":[{"id":"9570269467246898","short_id":306,"parent_id":"9570269467246595","alias":"remont_ustanovka_bytovojj_tekhniki","name":"Ремонт \/ установка бытовой техники","kind":"primary"},{"id":"9570269467252247","short_id":5655,"parent_id":"9570269467246607","alias":"remont_promyshlennogo_oborudovaniya","name":"Ремонт промышленного оборудования","kind":"primary"},{"id":"9570269467297463","short_id":50871,"parent_id":"9570269467246595","alias":"zapchasti_aksessuary_dlya_bytovojj_tekhniki","name":"Запчасти \/ аксессуары для бытовой техники","kind":"additional"}],"reviews":{"items":[{"tag":"foursquare","is_reviewable":true}],"org_rating":0,"is_reviewable":false,"org_review_count":0,"is_reviewable_on_flamp":true,"reg_bc_url":"https:\/\/stat.api.2gis.ru\/?v=2.0&hash=885c9d88G448312319A98G2Gc2hdc344G6G5G8I2G2I9G3HAfEpy397I3378G720034995491Ah2uv08555A221BB368159A2H13H0I2fe"},"flags":{"photos":false},"external_content":[]},{"id":"70000001018121848_B8579488G448312319A98G2Gcae5cg44G6G5G8I2G1IAG3HAfEpy397I3378G7200349954915h2uv08555A222A7A68159A2H0JH97","region_id":"68","type":"branch","name":"Moneytor, ТОО, сервис-центр","name_ex":{"primary":"Moneytor, ТОО","extension":"сервис-центр"},"point":{"lon":71.451647,"lat":51.16083},"reg_bc_url":"https:\/\/stat.api.2gis.ru\/?v=2.0&hash=98559188G448312319A98G2Gc239cf44G6G5G8I2G2IAG3HAfEpy397I3378G7200349954913h2uv08555A222A7A68159A2H0J1G2e9","adm_div":[],"address":{"components":[{"id":"9571081216067917","type":"street_number","number":"9","street":"Тархана"}],"building_id":"9570784863330883","building_code":"Z00Y3Y5","reg_bc_url":"https:\/\/stat.api.2gis.ru\/?v=2.0&hash=A85e9788G448312319A98G2Gcf97c344G6G5G8I2G2IAG3HAfEpy397I3378G720034995491gh2uv08555A222A7A68159A2H16H0I2e7"},"address_name":"Тархана, 9","address_comment":"1 офис","org":{"id":"70000001018121845","name":"Moneytor, ТОО, сервис-центр","branch_count":1},"contact_groups":[{"contacts":[{"type":"phone","value":"+77078586529","text":"+7‒707‒858‒65‒29","reg_bc_url":"https:\/\/stat.api.2gis.ru\/?v=2.0&hash=585g9388G448312319A98G2Gc7B8cb44G6G5G8I2G2IAG3HAfEpy397I3378G720034995491gh2uv08555A222A7A68159A2H2J1G232"},{"type":"phone","value":"+77013400957","text":"+7‒701‒340‒09‒57","reg_bc_url":"https:\/\/stat.api.2gis.ru\/?v=2.0&hash=i8519c88G448312319A98G2Gc8c8c444G6G5G8I2G2IAG3HAfEpy397I3378G7200349954911h2uv08555A222A7A68159A2H2J1G2gc"},{"type":"phone","value":"+77172481892","text":"+7 (7172) 48‒18‒92","reg_bc_url":"https:\/\/stat.api.2gis.ru\/?v=2.0&hash=885d9g88G448312319A98G2Gc38Ac744G6G5G8I2G2IAG3HAfEpy397I3378G720034995491Ah2uv08555A222A7A68159A2H2J1G2A4"},{"type":"website","value":"http:\/\/link.2gis.ru\/1.2\/18D07B40\/online\/20160801\/project68\/70000001018121848\/2gis.ru\/e85g9888G448312319A98G2Gcbdhc244G6G5G8I2G2IAG3HAfEpy397I3378G720034995491fh2uv08555A222A7A68159A2H4J1G2ff?http:\/\/moneytor.kz","text":"moneytor.kz"}]}],"schedule":{"Mon":{"working_hours":[{"to":"19:00","from":"10:00"}]},"Tue":{"working_hours":[{"to":"19:00","from":"10:00"}]},"Wed":{"working_hours":[{"to":"19:00","from":"10:00"}]},"Thu":{"working_hours":[{"to":"19:00","from":"10:00"}]},"Fri":{"working_hours":[{"to":"19:00","from":"10:00"}]},"Sat":{"working_hours":[{"to":"13:00","from":"10:00"}]}},"rubrics":[{"id":"9570269467252247","short_id":5655,"parent_id":"9570269467246607","alias":"remont_promyshlennogo_oborudovaniya","name":"Ремонт промышленного оборудования","kind":"primary"},{"id":"9570269467246898","short_id":306,"parent_id":"9570269467246595","alias":"remont_ustanovka_bytovojj_tekhniki","name":"Ремонт \/ установка бытовой техники","kind":"primary"}],"reviews":{"items":[{"tag":"foursquare","is_reviewable":true}],"org_rating":0,"is_reviewable":false,"org_review_count":0,"is_reviewable_on_flamp":true,"reg_bc_url":"https:\/\/stat.api.2gis.ru\/?v=2.0&hash=98549788G448312319A98G2Gc686cA44G6G5G8I2G2IAG3HAfEpy397I3378G720034995491dh2uv08555A222A7A68159A2H13H0I2fd"},"flags":{"photos":false},"external_content":[]},{"id":"70000001018061443_785f9188G4483123198898G2ce4gcA44G6G5G8I2G1I20J1HfEpy397I3378G72003978A2716h2uv08555A162675A68357H2G3HG32","region_id":"68","type":"branch","name":"Absolut Service, сервисная компания","name_ex":{"primary":"Absolut Service","extension":"сервисная компания"},"point":{"lon":71.489657,"lat":51.157003},"reg_bc_url":"https:\/\/stat.api.2gis.ru\/?v=2.0&hash=68549688G4483123198898G2cfdfc244G6G5G8I2G2I20J1HfEpy397I3378G72003978A2713h2uv08555A162675A68357H2G3H0I227","adm_div":[],"address":{"components":[{"id":"9571081216084235","type":"street_number","number":"6\/1","street":"Манаса"}],"building_id":"9570784863343923","reg_bc_url":"https:\/\/stat.api.2gis.ru\/?v=2.0&hash=68599g88G4483123198898G2cdh2c444G6G5G8I2G2I20J1HfEpy397I3378G72003978A271gh2uv08555A162675A68357H2G44G2I1bB"},"address_name":"Манаса, 6\/1","address_comment":"1 этаж","org":{"id":"70000001018061442","name":"Absolut Service, сервисная компания","branch_count":1},"contact_groups":[{"contacts":[{"type":"phone","value":"+77172780586","text":"+7 (7172) 78‒05‒86","reg_bc_url":"https:\/\/stat.api.2gis.ru\/?v=2.0&hash=58549g88G4483123198898G2c599cb44G6G5G8I2G2I20J1HfEpy397I3378G72003978A2715h2uv08555A162675A68357H2G5H0I24c"},{"type":"phone","value":"+77072692909","text":"+7‒707‒269‒29‒09","reg_bc_url":"https:\/\/stat.api.2gis.ru\/?v=2.0&hash=d85A9988G4483123198898G2c6c9c244G6G5G8I2G2I20J1HfEpy397I3378G72003978A2717h2uv08555A162675A68357H2G5H0I21e"},{"type":"phone","value":"+77172456167","text":"+7 (7172) 45‒61‒67","reg_bc_url":"https:\/\/stat.api.2gis.ru\/?v=2.0&hash=385b9188G4483123198898G2c222c844G6G5G8I2G2I20J1HfEpy397I3378G72003978A2716h2uv08555A162675A68357H2G5H0I2cb"},{"type":"website","value":"http:\/\/link.2gis.ru\/1.2\/271D54B3\/online\/20160801\/project68\/70000001018061443\/2gis.ru\/A85d9b88G4483123198898G2c57dc544G6G5G8I2G2I20J1HfEpy397I3378G72003978A2716h2uv08555A162675A68357H2G7H0I23d?http:\/\/www.a-abbsolut.asn.kz","text":"www.a-abbsolut.asn.kz"},{"type":"website","value":"http:\/\/link.2gis.ru\/1.2\/B319D584\/online\/20160801\/project68\/70000001018061443\/2gis.ru\/485A9988G4483123198898G2cd2hc444G6G5G8I2G2I20J1HfEpy397I3378G72003978A271gh2uv08555A162675A68357H2G7H0I23d?http:\/\/www.absolutservice.kz","text":"www.absolutservice.kz"}]}],"schedule":{"Mon":{"working_hours":[{"to":"20:00","from":"10:00"}]},"Tue":{"working_hours":[{"to":"20:00","from":"10:00"}]},"Wed":{"working_hours":[{"to":"20:00","from":"10:00"}]},"Thu":{"working_hours":[{"to":"20:00","from":"10:00"}]},"Fri":{"working_hours":[{"to":"20:00","from":"10:00"}]},"Sat":{"working_hours":[{"to":"20:00","from":"10:00"}]},"Sun":{"working_hours":[{"to":"20:00","from":"10:00"}]}},"rubrics":[{"id":"9570269467246898","short_id":306,"parent_id":"9570269467246595","alias":"remont_ustanovka_bytovojj_tekhniki","name":"Ремонт \/ установка бытовой техники","kind":"primary"}],"reviews":{"items":[{"tag":"foursquare","is_reviewable":true}],"org_rating":0,"is_reviewable":false,"org_review_count":0,"is_reviewable_on_flamp":true,"reg_bc_url":"https:\/\/stat.api.2gis.ru\/?v=2.0&hash=985e9388G4483123198898G2ce7fc144G6G5G8I2G2I20J1HfEpy397I3378G72003978A271ch2uv08555A162675A68357H2G41G2I195"},"flags":{"photos":false},"external_content":[]},{"id":"70000001018112204_e8539488G4483123198898G2c6fccg44G6G5G8I2G1I21J1HfEpy397I3378G72003978A271gh2uv08555A213436A68357H2G3HG3A","region_id":"68","type":"branch","name":"Ремстирмаш-Астана, выездная сервисная компания","name_ex":{"primary":"Ремстирмаш-Астана","extension":"выездная сервисная компания"},"point":{"lon":71.465333,"lat":51.146679},"reg_bc_url":"https:\/\/stat.api.2gis.ru\/?v=2.0&hash=e85g9b88G4483123198898G2c6c8c644G6G5G8I2G2I21J1HfEpy397I3378G72003978A271bh2uv08555A213436A68357H2G3H0I2AA","adm_div":[{"id":"9570810633125898","name":"1-й м-н","type":"living_area"}],"address":{"components":[{"id":"9571081216067985","type":"street_number","number":"14\/3","street":"Петрова"}],"building_id":"9570784863324953","reg_bc_url":"https:\/\/stat.api.2gis.ru\/?v=2.0&hash=38579988G4483123198898G2c4h2cg44G6G5G8I2G2I21J1HfEpy397I3378G72003978A271eh2uv08555A213436A68357H2G44G2I17B"},"address_name":"Петрова, 14\/3","org":{"id":"70000001018112203","name":"Ремстирмаш-Астана, выездная сервисная компания","branch_count":1},"contact_groups":[{"contacts":[{"type":"phone","value":"+77751838547","text":"+7‒775‒183‒85‒47","reg_bc_url":"https:\/\/stat.api.2gis.ru\/?v=2.0&hash=78599288G4483123198898G2c8hhcf44G6G5G8I2G2I21J1HfEpy397I3378G72003978A271fh2uv08555A213436A68357H2G5H0I226"},{"type":"website","value":"http:\/\/link.2gis.ru\/1.2\/BD13F506\/online\/20160801\/project68\/70000001018112204\/2gis.ru\/A85A9d88G4483123198898G2ce2ccc44G6G5G8I2G2I21J1HfEpy397I3378G72003978A2716h2uv08555A213436A68357H2G7H0I239?http:\/\/rem-centre.kz","text":"rem-centre.kz"},{"type":"vkontakte","value":"https:\/\/vk.com\/remcentre","text":"https:\/\/vk.com\/remcentre","reg_bc_url":"https:\/\/stat.api.2gis.ru\/?v=2.0&hash=B85g9e88G4483123198898G2c3B6cc44G6G5G8I2G2I21J1HfEpy397I3378G72003978A271ch2uv08555A213436A68357H2G51G2I1ch"}]}],"schedule":{"Mon":{"working_hours":[{"to":"22:00","from":"10:00"}]},"Tue":{"working_hours":[{"to":"22:00","from":"10:00"}]},"Wed":{"working_hours":[{"to":"22:00","from":"10:00"}]},"Thu":{"working_hours":[{"to":"22:00","from":"10:00"}]},"Fri":{"working_hours":[{"to":"22:00","from":"10:00"}]},"Sat":{"working_hours":[{"to":"22:00","from":"10:00"}]},"Sun":{"working_hours":[{"to":"22:00","from":"10:00"}]},"comment":"по предварительной записи: пн-вс"},"rubrics":[{"id":"9570269467246898","short_id":306,"parent_id":"9570269467246595","alias":"remont_ustanovka_bytovojj_tekhniki","name":"Ремонт \/ установка бытовой техники","kind":"primary"}],"reviews":{"items":[{"tag":"foursquare","is_reviewable":true}],"org_rating":0,"is_reviewable":false,"org_review_count":0,"is_reviewable_on_flamp":true,"reg_bc_url":"https:\/\/stat.api.2gis.ru\/?v=2.0&hash=B85g9388G4483123198898G2c87dc744G6G5G8I2G2I21J1HfEpy397I3378G72003978A2713h2uv08555A213436A68357H2G41G2I147"},"flags":{"photos":false},"external_content":[]},{"id":"70000001018093702_985A9288G4483123198898G2ce9Acg44G6G5G8I2G1I22J1HfEpy397I3378G72003978A271gh2uv08555A194934A68357H2G3HG5e","region_id":"68","type":"branch","name":"Империя услуг, многопрофильная компания","name_ex":{"primary":"Империя услуг","extension":"многопрофильная компания"},"point":null,"reg_bc_url":"https:\/\/stat.api.2gis.ru\/?v=2.0&hash=88529b88G4483123198898G2c4A2cA44G6G5G8I2G2I22J1HfEpy397I3378G72003978A2711h2uv08555A194934A68357H2G3H0I2cg","adm_div":[],"address":{"components":[{"type":"location","comment":"Астана"}],"reg_bc_url":"https:\/\/stat.api.2gis.ru\/?v=2.0&hash=885b9f88G4483123198898G2c339cg44G6G5G8I2G2I22J1HfEpy397I3378G72003978A271eh2uv08555A194934A68357H2G44G2I1dC"},"org":{"id":"70000001018093701","name":"Империя услуг, многопрофильная компания","branch_count":1},"contact_groups":[{"contacts":[{"type":"phone","value":"+77084251354","text":"+7‒708‒425‒13‒54","reg_bc_url":"https:\/\/stat.api.2gis.ru\/?v=2.0&hash=C8529888G4483123198898G2c378c244G6G5G8I2G2I22J1HfEpy397I3378G72003978A271Ah2uv08555A194934A68357H2G5H0I2bb"},{"type":"website","value":"http:\/\/link.2gis.ru\/1.2\/AEE3E24C\/online\/20160801\/project68\/70000001018093702\/2gis.ru\/48539g88G4483123198898G2cf4Bc344G6G5G8I2G2I22J1HfEpy397I3378G72003978A2713h2uv08555A194934A68357H2G7H0I2b1?http:\/\/the-imperia.ru","text":"the-imperia.ru"},{"type":"vkontakte","value":"https:\/\/vk.com\/empire_service","text":"https:\/\/vk.com\/empire_service","reg_bc_url":"https:\/\/stat.api.2gis.ru\/?v=2.0&hash=68549488G4483123198898G2c83ecf44G6G5G8I2G2I22J1HfEpy397I3378G72003978A2713h2uv08555A194934A68357H2G51G2I1f8"},{"type":"instagram","value":"https:\/\/instagram.com\/imperia_uslug_astana","text":"https:\/\/instagram.com\/imperia_uslug_astana","reg_bc_url":"https:\/\/stat.api.2gis.ru\/?v=2.0&hash=C8579e88G4483123198898G2cb7dcg44G6G5G8I2G2I22J1HfEpy397I3378G72003978A271Ah2uv08555A194934A68357H2G51G2I1A6"}]}],"schedule":{"Mon":{"working_hours":[{"to":"22:00","from":"09:00"}]},"Tue":{"working_hours":[{"to":"22:00","from":"09:00"}]},"Wed":{"working_hours":[{"to":"22:00","from":"09:00"}]},"Thu":{"working_hours":[{"to":"22:00","from":"09:00"}]},"Fri":{"working_hours":[{"to":"22:00","from":"09:00"}]},"Sat":{"working_hours":[{"to":"22:00","from":"09:00"}]},"Sun":{"working_hours":[{"to":"22:00","from":"09:00"}]}},"rubrics":[{"id":"9570269467246871","short_id":279,"parent_id":"9570269467246601","alias":"ehlektromontazhnye_raboty","name":"Электромонтажные работы","kind":"primary"},{"id":"9570269467350789","short_id":104197,"parent_id":"9570269467246601","alias":"remont_ustanovka_santekhnicheskogo_oborudovaniya","name":"Ремонт \/ установка сантехнического оборудования","kind":"primary"},{"id":"9570269467247242","short_id":650,"parent_id":"9570269467246595","alias":"remont_kompyuterov","name":"Ремонт компьютеров","kind":"primary"},{"id":"9570269467246868","short_id":276,"parent_id":"9570269467246601","alias":"remont_otdelka_pomeshhenijj","name":"Ремонт \/ отделка помещений","kind":"primary"},{"id":"9570269467246898","short_id":306,"parent_id":"9570269467246595","alias":"remont_ustanovka_bytovojj_tekhniki","name":"Ремонт \/ установка бытовой техники","kind":"primary"}],"reviews":{"items":[{"tag":"foursquare","is_reviewable":true}],"org_rating":0,"is_reviewable":false,"org_review_count":0,"is_reviewable_on_flamp":true,"reg_bc_url":"https:\/\/stat.api.2gis.ru\/?v=2.0&hash=g8599388G4483123198898G2c928cb44G6G5G8I2G2I22J1HfEpy397I3378G72003978A271ch2uv08555A194934A68357H2G41G2I1c9"},"flags":{"photos":false},"external_content":[]},{"id":"70000001018519576_f8589A88G4483123198898G2cf65c944G6G5G8I2G1I23J1HfEpy397I3378G72003978A271eh2uv08555A61A7A8A68357H2G3HG52","region_id":"68","type":"branch","name":"Argo KZ, ТОО","name_ex":{"primary":"Argo KZ, ТОО"},"point":{"lon":71.418233,"lat":51.1721},"reg_bc_url":"https:\/\/stat.api.2gis.ru\/?v=2.0&hash=685e9588G4483123198898G2c8Bec944G6G5G8I2G2I23J1HfEpy397I3378G72003978A2716h2uv08555A61A7A8A68357H2G3H0I2f5","adm_div":[],"address":{"components":[{"id":"9571081216067990","type":"street_number","number":"25","street":"Бейбитшилик"}],"building_id":"9570784863333007","reg_bc_url":"https:\/\/stat.api.2gis.ru\/?v=2.0&hash=e8529f88G4483123198898G2c36ecb44G6G5G8I2G2I23J1HfEpy397I3378G72003978A2714h2uv08555A61A7A8A68357H2G44G2I19h"},"address_name":"Бейбитшилик, 25","address_comment":"цокольный этаж","org":{"id":"70000001018519575","name":"Argo KZ, ТОО","branch_count":1},"contact_groups":[{"contacts":[{"type":"phone","value":"+77071011493","text":"+7‒707‒101‒14‒93","reg_bc_url":"https:\/\/stat.api.2gis.ru\/?v=2.0&hash=B85b9c88G4483123198898G2c9fBc844G6G5G8I2G2I23J1HfEpy397I3378G72003978A2712h2uv08555A61A7A8A68357H2G5H0I239"},{"type":"website","value":"http:\/\/link.2gis.ru\/1.2\/CFFAA5A6\/online\/20160801\/project68\/70000001018519576\/2gis.ru\/B85c9788G4483123198898G2c9g8c544G6G5G8I2G2I23J1HfEpy397I3378G72003978A271ch2uv08555A61A7A8A68357H2G7H0I287?http:\/\/argokz.kz","text":"argokz.kz"}]}],"schedule":{"Mon":{"working_hours":[{"to":"24:00","from":"00:00"}]},"Tue":{"working_hours":[{"to":"24:00","from":"00:00"}]},"Wed":{"working_hours":[{"to":"24:00","from":"00:00"}]},"Thu":{"working_hours":[{"to":"24:00","from":"00:00"}]},"Fri":{"working_hours":[{"to":"24:00","from":"00:00"}]},"Sat":{"working_hours":[{"to":"24:00","from":"00:00"}]},"Sun":{"working_hours":[{"to":"24:00","from":"00:00"}]}},"rubrics":[{"id":"9570269467252247","short_id":5655,"parent_id":"9570269467246607","alias":"remont_promyshlennogo_oborudovaniya","name":"Ремонт промышленного оборудования","kind":"primary"},{"id":"9570269467246898","short_id":306,"parent_id":"9570269467246595","alias":"remont_ustanovka_bytovojj_tekhniki","name":"Ремонт \/ установка бытовой техники","kind":"primary"},{"id":"9570269467271404","short_id":24812,"parent_id":"9570269467246607","alias":"remont_obsluzhivanie_klimaticheskogo_oborudovaniya","name":"Ремонт \/ обслуживание климатического оборудования","kind":"additional"}],"reviews":{"items":[{"tag":"foursquare","is_reviewable":true}],"org_rating":0,"is_reviewable":false,"org_review_count":0,"is_reviewable_on_flamp":true,"reg_bc_url":"https:\/\/stat.api.2gis.ru\/?v=2.0&hash=g8589988G4483123198898G2c83cc644G6G5G8I2G2I23J1HfEpy397I3378G72003978A2719h2uv08555A61A7A8A68357H2G41G2I13i"},"flags":{"photos":false},"external_content":[]},{"id":"70000001023355361_i8579A88G4483123248898G2c7cBcg44G6G5G8I2G1I24J1HfEpy397I3378G72003978A2713h2uv08555A456593A68357H2G3HG22","region_id":"68","type":"branch","name":"Мастерская по ремонту бытовой техники, ИП Аселя","name_ex":{"primary":"Мастерская по ремонту бытовой техники","extension":"ИП Аселя"},"point":{"lon":71.3914,"lat":51.198664},"reg_bc_url":"https:\/\/stat.api.2gis.ru\/?v=2.0&hash=B85b9c88G4483123248898G2c397cb44G6G5G8I2G2I24J1HfEpy397I3378G72003978A2714h2uv08555A456593A68357H2G3H0I2A1","adm_div":[],"address":{"components":[{"id":"9571081216080671","type":"street_number","number":"29","street":"Карасай батыра"}],"building_id":"9570784863331300","building_code":"Z10P4E1","reg_bc_url":"https:\/\/stat.api.2gis.ru\/?v=2.0&hash=f8569688G4483123248898G2c193c344G6G5G8I2G2I24J1HfEpy397I3378G72003978A271fh2uv08555A456593A68357H2G44G2I195"},"address_name":"Карасай батыра, 29","address_comment":"цокольный этаж","org":{"id":"70000001023355360","name":"Мастерская по ремонту бытовой техники, ИП Аселя","branch_count":1},"contact_groups":[{"contacts":[{"type":"phone","value":"+77172457789","text":"+7 (7172) 45‒77‒89","reg_bc_url":"https:\/\/stat.api.2gis.ru\/?v=2.0&hash=68579e88G4483123248898G2ceBec544G6G5G8I2G2I24J1HfEpy397I3378G72003978A2714h2uv08555A456593A68357H2G5H0I2dc"},{"type":"phone","value":"+77019988979","text":"+7‒701‒998‒89‒79","reg_bc_url":"https:\/\/stat.api.2gis.ru\/?v=2.0&hash=78589688G4483123248898G2cce8cg44G6G5G8I2G2I24J1HfEpy397I3378G72003978A271bh2uv08555A456593A68357H2G5H0I28A"},{"type":"website","value":"http:\/\/link.2gis.ru\/1.2\/9AE30E39\/online\/20160801\/project68\/70000001023355361\/2gis.ru\/585c9488G4483123248898G2c4A6cc44G6G5G8I2G2I24J1HfEpy397I3378G72003978A271eh2uv08555A456593A68357H2G7H0I2f1?http:\/\/remastana.kz","text":"remastana.kz"}]}],"schedule":{"Mon":{"working_hours":[{"to":"20:00","from":"09:00"}]},"Tue":{"working_hours":[{"to":"20:00","from":"09:00"}]},"Wed":{"working_hours":[{"to":"20:00","from":"09:00"}]},"Thu":{"working_hours":[{"to":"20:00","from":"09:00"}]},"Fri":{"working_hours":[{"to":"20:00","from":"09:00"}]},"Sat":{"working_hours":[{"to":"20:00","from":"09:00"}]},"Sun":{"working_hours":[{"to":"20:00","from":"09:00"}]}},"rubrics":[{"id":"9570269467246898","short_id":306,"parent_id":"9570269467246595","alias":"remont_ustanovka_bytovojj_tekhniki","name":"Ремонт \/ установка бытовой техники","kind":"primary"}],"reviews":{"items":[{"tag":"foursquare","is_reviewable":true}],"org_rating":0,"is_reviewable":false,"org_review_count":0,"is_reviewable_on_flamp":true,"reg_bc_url":"https:\/\/stat.api.2gis.ru\/?v=2.0&hash=38539d88G4483123248898G2c859c844G6G5G8I2G2I24J1HfEpy397I3378G72003978A271dh2uv08555A456593A68357H2G41G2I12h"},"flags":{"photos":false},"external_content":[]},{"id":"70000001018112166_88549788G4483123198898G2c4hece44G6G5G8I2G1I25J1HfEpy397I3378G72003978A271dh2uv08555A213398A68357H2G3HGhe","region_id":"68","type":"branch","name":"Останин М.С., ИП","name_ex":{"primary":"Останин М.С., ИП"},"point":{"lon":71.470972,"lat":51.137569},"reg_bc_url":"https:\/\/stat.api.2gis.ru\/?v=2.0&hash=C85g9188G4483123198898G2c57fc444G6G5G8I2G2I25J1HfEpy397I3378G72003978A271Ah2uv08555A213398A68357H2G3H0I2cg","adm_div":[{"id":"9570810633125895","name":"Юго-Восток(левая сторона) м-н","type":"living_area"}],"address":{"components":[{"id":"9571081216069780","type":"street_number","number":"4","street":"Бауыржан Момышулы"}],"building_id":"9570784863333444","reg_bc_url":"https:\/\/stat.api.2gis.ru\/?v=2.0&hash=48589588G4483123198898G2c7f8c844G6G5G8I2G2I25J1HfEpy397I3378G72003978A271fh2uv08555A213398A68357H2G44G2I14A"},"address_name":"Бауыржан Момышулы, 4","address_comment":"319 офис","org":{"id":"70000001018112165","name":"Останин М.С., ИП","branch_count":1},"contact_groups":[{"contacts":[{"type":"phone","value":"+77014128541","text":"+7‒701‒412‒85‒41","reg_bc_url":"https:\/\/stat.api.2gis.ru\/?v=2.0&hash=d85g9788G4483123198898G2c0f4c444G6G5G8I2G2I25J1HfEpy397I3378G72003978A271bh2uv08555A213398A68357H2G5H0I24A"},{"type":"phone","value":"+77172779085","text":"+7 (7172) 77‒90‒85","reg_bc_url":"https:\/\/stat.api.2gis.ru\/?v=2.0&hash=985g9c88G4483123198898G2c0edc844G6G5G8I2G2I25J1HfEpy397I3378G72003978A2714h2uv08555A213398A68357H2G5H0I2c8"},{"type":"website","value":"http:\/\/link.2gis.ru\/1.2\/51BEA8F2\/online\/20160801\/project68\/70000001018112166\/2gis.ru\/B85e9d88G4483123198898G2cch4c244G6G5G8I2G2I25J1HfEpy397I3378G72003978A271Ah2uv08555A213398A68357H2G7H0I284?http:\/\/remont-stiralnyh-mashin-v-astane.kz","text":"remont-stiralnyh-mashin-v-astane.kz"}]}],"schedule":{"Mon":{"working_hours":[{"to":"21:00","from":"09:00"}]},"Tue":{"working_hours":[{"to":"21:00","from":"09:00"}]},"Wed":{"working_hours":[{"to":"21:00","from":"09:00"}]},"Thu":{"working_hours":[{"to":"21:00","from":"09:00"}]},"Fri":{"working_hours":[{"to":"21:00","from":"09:00"}]},"Sat":{"working_hours":[{"to":"21:00","from":"09:00"}]},"Sun":{"working_hours":[{"to":"21:00","from":"09:00"}]}},"rubrics":[{"id":"9570269467246898","short_id":306,"parent_id":"9570269467246595","alias":"remont_ustanovka_bytovojj_tekhniki","name":"Ремонт \/ установка бытовой техники","kind":"primary"}],"reviews":{"items":[{"tag":"foursquare","is_reviewable":true}],"org_rating":0,"is_reviewable":false,"org_review_count":0,"is_reviewable_on_flamp":true,"reg_bc_url":"https:\/\/stat.api.2gis.ru\/?v=2.0&hash=78599c88G4483123198898G2c36dc744G6G5G8I2G2I25J1HfEpy397I3378G72003978A271ch2uv08555A213398A68357H2G41G2I19h"},"flags":{"photos":false},"external_content":[]},{"id":"70000001018072107_e8579b88G4483123198898G2c29BcA44G6G5G8I2G1I26J1HfEpy397I3378G72003978A2717h2uv08555A173339A68357H2G3HG28","region_id":"68","type":"branch","name":"PTN-Сервис, сервис-центр","name_ex":{"primary":"PTN-Сервис","extension":"сервис-центр"},"point":{"lon":71.47729,"lat":51.14828},"reg_bc_url":"https:\/\/stat.api.2gis.ru\/?v=2.0&hash=B8569d88G4483123198898G2c9c6c344G6G5G8I2G2I26J1HfEpy397I3378G72003978A2715h2uv08555A173339A68357H2G3H0I2fd","adm_div":[{"id":"9570810633125924","name":"6-й м-н","type":"living_area"}],"address":{"components":[{"id":"9571081216068309","type":"street_number","number":"23\/1","street":"Куйши Дина"}],"building_id":"9570784863334640","building_code":"Z00Y8Y7","reg_bc_url":"https:\/\/stat.api.2gis.ru\/?v=2.0&hash=h8519g88G4483123198898G2c9hgcg44G6G5G8I2G2I26J1HfEpy397I3378G72003978A271fh2uv08555A173339A68357H2G44G2I1b9"},"address_name":"Куйши Дина, 23\/1","address_comment":"цокольный этаж","org":{"id":"70000001018072106","name":"PTN-Сервис, сервис-центр","branch_count":1},"contact_groups":[{"contacts":[{"type":"phone","value":"+77172366455","text":"+7 (7172) 36‒64‒55","reg_bc_url":"https:\/\/stat.api.2gis.ru\/?v=2.0&hash=38599d88G4483123198898G2cf58c144G6G5G8I2G2I26J1HfEpy397I3378G72003978A2713h2uv08555A173339A68357H2G5H0I287"},{"type":"phone","value":"+77172352862","text":"+7 (7172) 35‒28‒62","reg_bc_url":"https:\/\/stat.api.2gis.ru\/?v=2.0&hash=d85d9188G4483123198898G2cd7fcf44G6G5G8I2G2I26J1HfEpy397I3378G72003978A2717h2uv08555A173339A68357H2G5H0I21e"},{"type":"phone","value":"+77078045241","text":"+7‒707‒804‒52‒41","reg_bc_url":"https:\/\/stat.api.2gis.ru\/?v=2.0&hash=485g9b88G4483123198898G2ccBec644G6G5G8I2G2I26J1HfEpy397I3378G72003978A2714h2uv08555A173339A68357H2G5H0I276"}]}],"schedule":{"Mon":{"working_hours":[{"to":"13:00","from":"09:00"},{"to":"18:00","from":"14:00"}]},"Tue":{"working_hours":[{"to":"13:00","from":"09:00"},{"to":"18:00","from":"14:00"}]},"Wed":{"working_hours":[{"to":"13:00","from":"09:00"},{"to":"18:00","from":"14:00"}]},"Thu":{"working_hours":[{"to":"13:00","from":"09:00"},{"to":"18:00","from":"14:00"}]},"Fri":{"working_hours":[{"to":"13:00","from":"09:00"},{"to":"18:00","from":"14:00"}]},"Sat":{"working_hours":[{"to":"13:00","from":"09:00"}]}},"rubrics":[{"id":"9570269467246898","short_id":306,"parent_id":"9570269467246595","alias":"remont_ustanovka_bytovojj_tekhniki","name":"Ремонт \/ установка бытовой техники","kind":"primary"}],"reviews":{"items":[{"tag":"foursquare","is_reviewable":true}],"org_rating":0,"is_reviewable":false,"org_review_count":0,"is_reviewable_on_flamp":true,"reg_bc_url":"https:\/\/stat.api.2gis.ru\/?v=2.0&hash=h8589788G4483123198898G2c2gBcb44G6G5G8I2G2I26J1HfEpy397I3378G72003978A2715h2uv08555A173339A68357H2G41G2I127"},"flags":{"photos":false},"external_content":[]},{"id":"70000001022946880_h85b9788G4483123238898G2cf37cb44G6G5G8I2G1I27J1HfEpy397I3378G72003978A271bh2uv08555AA47AB2A68357H2G3HG6e","region_id":"68","type":"branch","name":"Hi-Tech service, ТОО, компьютерный сервис-центр","name_ex":{"primary":"Hi-Tech service, ТОО","extension":"компьютерный сервис-центр"},"point":{"lon":71.465333,"lat":51.146679},"reg_bc_url":"https:\/\/stat.api.2gis.ru\/?v=2.0&hash=885c9A88G4483123238898G2ca9cc544G6G5G8I2G2I27J1HfEpy397I3378G72003978A271eh2uv08555AA47AB2A68357H2G3H0I26A","adm_div":[{"id":"9570810633125898","name":"1-й м-н","type":"living_area"}],"address":{"components":[{"id":"9571081216067985","type":"street_number","number":"14\/3","street":"Петрова"}],"building_id":"9570784863324953","reg_bc_url":"https:\/\/stat.api.2gis.ru\/?v=2.0&hash=h8579588G4483123238898G2cfc3c844G6G5G8I2G2I27J1HfEpy397I3378G72003978A271gh2uv08555AA47AB2A68357H2G44G2I138"},"address_name":"Петрова, 14\/3","address_comment":"цокольный этаж","org":{"id":"70000001022946879","name":"Hi-Tech service, ТОО, компьютерный сервис-центр","branch_count":1},"contact_groups":[{"contacts":[{"type":"phone","value":"+77011882363","text":"+7‒701‒188‒23‒63","reg_bc_url":"https:\/\/stat.api.2gis.ru\/?v=2.0&hash=685b9588G4483123238898G2c6eAc344G6G5G8I2G2I27J1HfEpy397I3378G72003978A2716h2uv08555AA47AB2A68357H2G5H0I285"},{"type":"phone","value":"+77072503035","text":"+7‒707‒250‒30‒35","reg_bc_url":"https:\/\/stat.api.2gis.ru\/?v=2.0&hash=38549988G4483123238898G2cc46c444G6G5G8I2G2I27J1HfEpy397I3378G72003978A271gh2uv08555AA47AB2A68357H2G5H0I28c"}]}],"schedule":{"Mon":{"working_hours":[{"to":"20:00","from":"10:00"}]},"Tue":{"working_hours":[{"to":"20:00","from":"10:00"}]},"Wed":{"working_hours":[{"to":"20:00","from":"10:00"}]},"Thu":{"working_hours":[{"to":"20:00","from":"10:00"}]},"Fri":{"working_hours":[{"to":"20:00","from":"10:00"}]},"Sat":{"working_hours":[{"to":"20:00","from":"10:00"}]},"Sun":{"working_hours":[{"to":"20:00","from":"10:00"}]}},"rubrics":[{"id":"9570269467247242","short_id":650,"parent_id":"9570269467246595","alias":"remont_kompyuterov","name":"Ремонт компьютеров","kind":"primary"},{"id":"9570269467247259","short_id":667,"parent_id":"9570269467266124","alias":"remont_mobilnykh_ustrojjstv_svyazi","name":"Ремонт мобильных устройств связи","kind":"primary"},{"id":"9570269467247220","short_id":628,"parent_id":"9570269467246595","alias":"remont_orgtekhniki","name":"Ремонт оргтехники","kind":"primary"},{"id":"9570269467251010","short_id":4418,"parent_id":"9570269467246595","alias":"zapravka_kartridzhejj","name":"Заправка картриджей","kind":"additional"},{"id":"9570269467246898","short_id":306,"parent_id":"9570269467246595","alias":"remont_ustanovka_bytovojj_tekhniki","name":"Ремонт \/ установка бытовой техники","kind":"additional"}],"reviews":{"items":[{"tag":"foursquare","is_reviewable":true}],"org_rating":0,"is_reviewable":false,"org_review_count":0,"is_reviewable_on_flamp":true,"reg_bc_url":"https:\/\/stat.api.2gis.ru\/?v=2.0&hash=g85g9d88G4483123238898G2cb4Acc44G6G5G8I2G2I27J1HfEpy397I3378G72003978A2712h2uv08555AA47AB2A68357H2G41G2I1g7"},"flags":{"photos":false},"external_content":[]},{"id":"70000001019868756_88599488G44831231A8898G2caB5c844G6G5G8I2G1I28J1HfEpy397I3378G72003978A271fh2uv08555A969988A68357H2G3HG9A","region_id":"68","type":"branch","name":"Аарон, мастерская по ремонту бытовой техники","name_ex":{"primary":"Аарон","extension":"мастерская по ремонту бытовой техники"},"point":{"lon":71.43061,"lat":51.165473},"reg_bc_url":"https:\/\/stat.api.2gis.ru\/?v=2.0&hash=f8519288G44831231A8898G2c062cg44G6G5G8I2G2I28J1HfEpy397I3378G72003978A2711h2uv08555A969988A68357H2G3H0I281","adm_div":[],"address":{"components":[{"id":"9571081216087108","type":"street_number","number":"17","street":"Малика Габдуллина"}],"building_id":"9570784863358257","reg_bc_url":"https:\/\/stat.api.2gis.ru\/?v=2.0&hash=f85c9c88G44831231A8898G2cdg4c444G6G5G8I2G2I28J1HfEpy397I3378G72003978A2718h2uv08555A969988A68357H2G44G2I153"},"address_name":"Малика Габдуллина, 17","address_comment":"1 этаж","org":{"id":"70000001019868755","name":"Аарон, мастерская по ремонту бытовой техники","branch_count":1},"contact_groups":[{"contacts":[{"type":"phone","value":"+77172727824","text":"+7 (7172) 72‒78‒24","reg_bc_url":"https:\/\/stat.api.2gis.ru\/?v=2.0&hash=C8579688G44831231A8898G2c6f4c944G6G5G8I2G2I28J1HfEpy397I3378G72003978A2715h2uv08555A969988A68357H2G5H0I265"}]}],"schedule":{"Mon":{"working_hours":[{"to":"20:00","from":"08:00"}]},"Tue":{"working_hours":[{"to":"20:00","from":"08:00"}]},"Wed":{"working_hours":[{"to":"20:00","from":"08:00"}]},"Thu":{"working_hours":[{"to":"20:00","from":"08:00"}]},"Fri":{"working_hours":[{"to":"20:00","from":"08:00"}]},"Sat":{"working_hours":[{"to":"20:00","from":"08:00"}]},"Sun":{"working_hours":[{"to":"20:00","from":"08:00"}]}},"rubrics":[{"id":"9570269467247242","short_id":650,"parent_id":"9570269467246595","alias":"remont_kompyuterov","name":"Ремонт компьютеров","kind":"primary"},{"id":"9570269467246898","short_id":306,"parent_id":"9570269467246595","alias":"remont_ustanovka_bytovojj_tekhniki","name":"Ремонт \/ установка бытовой техники","kind":"primary"},{"id":"9570269467271404","short_id":24812,"parent_id":"9570269467246607","alias":"remont_obsluzhivanie_klimaticheskogo_oborudovaniya","name":"Ремонт \/ обслуживание климатического оборудования","kind":"primary"},{"id":"9570269467247553","short_id":961,"parent_id":"9570269467246595","alias":"remont_audio_video_cifrovojj_tekhniki","name":"Ремонт аудио \/ видео \/ цифровой техники","kind":"primary"}],"reviews":{"items":[{"tag":"foursquare","is_reviewable":true}],"org_rating":0,"is_reviewable":false,"org_review_count":0,"is_reviewable_on_flamp":true,"reg_bc_url":"https:\/\/stat.api.2gis.ru\/?v=2.0&hash=i85g9g88G44831231A8898G2c2f8c944G6G5G8I2G2I28J1HfEpy397I3378G72003978A2714h2uv08555A969988A68357H2G41G2I1cB"},"flags":{"photos":false},"external_content":[]},{"id":"70000001018511365_385A9588G4483123198898G2c98fc744G6G5G8I2G1I29J1HfEpy397I3378G72003978A2712h2uv08555A612597A68357H2G3HGA9","region_id":"68","type":"branch","name":"Выездная служба ремонта, ИП Ремсервис","name_ex":{"primary":"Выездная служба ремонта","extension":"ИП Ремсервис"},"point":null,"reg_bc_url":"https:\/\/stat.api.2gis.ru\/?v=2.0&hash=f8559e88G4483123198898G2c563ce44G6G5G8I2G2I29J1HfEpy397I3378G72003978A271eh2uv08555A612597A68357H2G3H0I26g","adm_div":[],"address":{"components":[{"type":"location","comment":"Астана"}],"reg_bc_url":"https:\/\/stat.api.2gis.ru\/?v=2.0&hash=g8539888G4483123198898G2ceB2ce44G6G5G8I2G2I29J1HfEpy397I3378G72003978A271Ah2uv08555A612597A68357H2G44G2I1AA"},"org":{"id":"70000001018511364","name":"Выездная служба ремонта, ИП Ремсервис","branch_count":1},"contact_groups":[{"contacts":[{"type":"phone","value":"+77474150695","text":"+7‒747‒415‒06‒95","reg_bc_url":"https:\/\/stat.api.2gis.ru\/?v=2.0&hash=e8539b88G4483123198898G2c29cc844G6G5G8I2G2I29J1HfEpy397I3378G72003978A271bh2uv08555A612597A68357H2G5H0I23c"},{"type":"website","value":"http:\/\/link.2gis.ru\/1.2\/ED4C168D\/online\/20160801\/project68\/70000001018511365\/2gis.ru\/e8569688G4483123198898G2cef9c644G6G5G8I2G2I29J1HfEpy397I3378G72003978A271ch2uv08555A612597A68357H2G7H0I25b?http:\/\/remservis2012.satu.kz","text":"remservis2012.satu.kz"}]}],"schedule":{"Mon":{"working_hours":[{"to":"13:00","from":"10:00"},{"to":"20:00","from":"14:00"}]},"Tue":{"working_hours":[{"to":"13:00","from":"10:00"},{"to":"20:00","from":"14:00"}]},"Wed":{"working_hours":[{"to":"13:00","from":"10:00"},{"to":"20:00","from":"14:00"}]},"Thu":{"working_hours":[{"to":"13:00","from":"10:00"},{"to":"20:00","from":"14:00"}]},"Fri":{"working_hours":[{"to":"13:00","from":"10:00"},{"to":"20:00","from":"14:00"}]},"Sat":{"working_hours":[{"to":"13:00","from":"10:00"},{"to":"20:00","from":"14:00"}]},"Sun":{"working_hours":[{"to":"13:00","from":"10:00"},{"to":"20:00","from":"14:00"}]},"comment":"по предварительной записи: пн-вс"},"rubrics":[{"id":"9570269467246898","short_id":306,"parent_id":"9570269467246595","alias":"remont_ustanovka_bytovojj_tekhniki","name":"Ремонт \/ установка бытовой техники","kind":"primary"}],"reviews":{"items":[{"tag":"foursquare","is_reviewable":true}],"org_rating":0,"is_reviewable":false,"org_review_count":0,"is_reviewable_on_flamp":true,"reg_bc_url":"https:\/\/stat.api.2gis.ru\/?v=2.0&hash=485f9488G4483123198898G2cd56c744G6G5G8I2G2I29J1HfEpy397I3378G72003978A271Ah2uv08555A612597A68357H2G41G2I1eg"},"flags":{"photos":false},"external_content":[]},{"id":"70000001023663375_68539e88G4483123248898G2c3g2ce44G6G5G8I2G1I30J1HfEpy397I3378G72003978A271Ah2uv08555A7645A7A68357H2G3HGeB","region_id":"68","type":"branch","name":"Мастерская по ремонту бытовой техники","name_ex":{"primary":"Мастерская по ремонту бытовой техники"},"point":{"lon":71.418031,"lat":51.181532},"reg_bc_url":"https:\/\/stat.api.2gis.ru\/?v=2.0&hash=B85e9388G4483123248898G2c887c644G6G5G8I2G2I30J1HfEpy397I3378G72003978A271ch2uv08555A7645A7A68357H2G3H0I2fb","adm_div":[],"address":{"components":[{"id":"9571081216067815","type":"street_number","number":"38\/1","street":"Московская"}],"building_id":"9570784863340667","reg_bc_url":"https:\/\/stat.api.2gis.ru\/?v=2.0&hash=e8569588G4483123248898G2c4A2ce44G6G5G8I2G2I30J1HfEpy397I3378G72003978A271ch2uv08555A7645A7A68357H2G44G2I19f"},"address_name":"Московская, 38\/1","address_comment":"цокольный этаж","org":{"id":"70000001023663374","name":"Мастерская по ремонту бытовой техники","branch_count":1},"contact_groups":[{"contacts":[{"type":"phone","value":"+77172626307","text":"+7 (7172) 62‒63‒07","reg_bc_url":"https:\/\/stat.api.2gis.ru\/?v=2.0&hash=A8569688G4483123248898G2cbBfc144G6G5G8I2G2I30J1HfEpy397I3378G72003978A2718h2uv08555A7645A7A68357H2G5H0I2g4"},{"type":"phone","value":"+77016289527","text":"+7‒701‒628‒95‒27","reg_bc_url":"https:\/\/stat.api.2gis.ru\/?v=2.0&hash=785b9688G4483123248898G2c573cg44G6G5G8I2G2I30J1HfEpy397I3378G72003978A271ch2uv08555A7645A7A68357H2G5H0I2d9"},{"type":"phone","value":"+77076289527","text":"+7‒707‒628‒95‒27","reg_bc_url":"https:\/\/stat.api.2gis.ru\/?v=2.0&hash=i8529388G4483123248898G2cffec444G6G5G8I2G2I30J1HfEpy397I3378G72003978A2716h2uv08555A7645A7A68357H2G5H0I2g4"},{"type":"website","value":"http:\/\/link.2gis.ru\/1.2\/B382987F\/online\/20160801\/project68\/70000001023663375\/2gis.ru\/78569588G4483123248898G2c9dBcc44G6G5G8I2G2I30J1HfEpy397I3378G72003978A271dh2uv08555A7645A7A68357H2G7H0I25d?http:\/\/xn--90ahvon7c.kz","text":"рембыт.kz"}]}],"schedule":{"Mon":{"working_hours":[{"to":"21:00","from":"09:00"}]},"Tue":{"working_hours":[{"to":"21:00","from":"09:00"}]},"Wed":{"working_hours":[{"to":"21:00","from":"09:00"}]},"Thu":{"working_hours":[{"to":"21:00","from":"09:00"}]},"Fri":{"working_hours":[{"to":"21:00","from":"09:00"}]},"Sat":{"working_hours":[{"to":"21:00","from":"09:00"}]}},"rubrics":[{"id":"9570269467246898","short_id":306,"parent_id":"9570269467246595","alias":"remont_ustanovka_bytovojj_tekhniki","name":"Ремонт \/ установка бытовой техники","kind":"primary"}],"reviews":{"items":[{"tag":"foursquare","is_reviewable":true}],"org_rating":0,"is_reviewable":false,"org_review_count":0,"is_reviewable_on_flamp":true,"reg_bc_url":"https:\/\/stat.api.2gis.ru\/?v=2.0&hash=d8569c88G4483123248898G2ca27c444G6G5G8I2G2I30J1HfEpy397I3378G72003978A2717h2uv08555A7645A7A68357H2G41G2I14B"},"flags":{"photos":false},"external_content":[]},{"id":"70000001018114487_78529e88G4483123198898G2ccc9c144G6G5G8I2G1I31J1HfEpy397I3378G72003978A2712h2uv08555A2156B9A68357H2G3HGdA","region_id":"68","type":"branch","name":"Мастерская по ремонту холодильников, ИП Сервис плюс","name_ex":{"primary":"Мастерская по ремонту холодильников","extension":"ИП Сервис плюс"},"point":{"lon":71.419266,"lat":51.187081},"reg_bc_url":"https:\/\/stat.api.2gis.ru\/?v=2.0&hash=68529d88G4483123198898G2cbg6c644G6G5G8I2G2I31J1HfEpy397I3378G72003978A2719h2uv08555A2156B9A68357H2G3H0I28e","adm_div":[],"address":{"components":[{"id":"9571081216067712","type":"street_number","number":"37\/1","street":"Алии Молдагуловой"}],"building_id":"9570784863346352","reg_bc_url":"https:\/\/stat.api.2gis.ru\/?v=2.0&hash=38589488G4483123198898G2ceBhc644G6G5G8I2G2I31J1HfEpy397I3378G72003978A2715h2uv08555A2156B9A68357H2G44G2I15e"},"address_name":"Алии Молдагуловой, 37\/1","address_comment":"206 кабинет; 2 этаж","org":{"id":"70000001018114486","name":"Мастерская по ремонту холодильников, ИП Сервис плюс","branch_count":1},"contact_groups":[{"contacts":[{"type":"phone","value":"+77172311202","text":"+7 (7172) 31‒12‒02","reg_bc_url":"https:\/\/stat.api.2gis.ru\/?v=2.0&hash=f8589188G4483123198898G2c6g3cd44G6G5G8I2G2I31J1HfEpy397I3378G72003978A271Ah2uv08555A2156B9A68357H2G5H0I23e"},{"type":"phone","value":"+77015001777","text":"+7‒701‒500‒17‒77","reg_bc_url":"https:\/\/stat.api.2gis.ru\/?v=2.0&hash=d85c9388G4483123198898G2cac6c344G6G5G8I2G2I31J1HfEpy397I3378G72003978A271Ah2uv08555A2156B9A68357H2G5H0I2g2"}]}],"schedule":{"Mon":{"working_hours":[{"to":"22:00","from":"08:00"}]},"Tue":{"working_hours":[{"to":"22:00","from":"08:00"}]},"Wed":{"working_hours":[{"to":"22:00","from":"08:00"}]},"Thu":{"working_hours":[{"to":"22:00","from":"08:00"}]},"Fri":{"working_hours":[{"to":"22:00","from":"08:00"}]},"Sat":{"working_hours":[{"to":"22:00","from":"08:00"}]},"Sun":{"working_hours":[{"to":"22:00","from":"08:00"}]}},"rubrics":[{"id":"9570269467246898","short_id":306,"parent_id":"9570269467246595","alias":"remont_ustanovka_bytovojj_tekhniki","name":"Ремонт \/ установка бытовой техники","kind":"primary"}],"reviews":{"items":[{"tag":"foursquare","is_reviewable":true}],"org_rating":0,"is_reviewable":false,"org_review_count":0,"is_reviewable_on_flamp":true,"reg_bc_url":"https:\/\/stat.api.2gis.ru\/?v=2.0&hash=f8579888G4483123198898G2c255c544G6G5G8I2G2I31J1HfEpy397I3378G72003978A2717h2uv08555A2156B9A68357H2G41G2I15h"},"flags":{"photos":false},"external_content":[]},{"id":"70000001018129906_48529A88G4483123198898G2c2hfcb44G6G5G8I2G1I32J1HfEpy397I3378G72003978A2717h2uv08555A22AB38A68357H2G3HG3c","region_id":"68","type":"branch","name":"Столичный, сервис-центр","name_ex":{"primary":"Столичный","extension":"сервис-центр"},"point":{"lon":71.481031,"lat":51.148639},"reg_bc_url":"https:\/\/stat.api.2gis.ru\/?v=2.0&hash=A85d9g88G4483123198898G2c3hcc644G6G5G8I2G2I32J1HfEpy397I3378G72003978A271gh2uv08555A22AB38A68357H2G3H0I25f","adm_div":[],"address":{"components":[{"id":"9571081216068461","type":"street_number","number":"28","street":"Куйши Дина"}],"building_id":"9570784863332593","building_code":"Z00Y9A7","reg_bc_url":"https:\/\/stat.api.2gis.ru\/?v=2.0&hash=f85b9888G4483123198898G2c7fcc444G6G5G8I2G2I32J1HfEpy397I3378G72003978A271eh2uv08555A22AB38A68357H2G44G2I14i"},"address_name":"Куйши Дина, 28","address_comment":"цокольный этаж","org":{"id":"70000001018129905","name":"Столичный, сервис-центр","branch_count":1},"contact_groups":[{"contacts":[{"type":"phone","value":"+77172420808","text":"+7 (7172) 42‒08‒08","reg_bc_url":"https:\/\/stat.api.2gis.ru\/?v=2.0&hash=885A9e88G4483123198898G2c2A6cA44G6G5G8I2G2I32J1HfEpy397I3378G72003978A271ch2uv08555A22AB38A68357H2G5H0I272"}]}],"schedule":{"Mon":{"working_hours":[{"to":"18:00","from":"09:00"}]},"Tue":{"working_hours":[{"to":"18:00","from":"09:00"}]},"Wed":{"working_hours":[{"to":"18:00","from":"09:00"}]},"Thu":{"working_hours":[{"to":"18:00","from":"09:00"}]},"Fri":{"working_hours":[{"to":"18:00","from":"09:00"}]}},"rubrics":[{"id":"9570269467246898","short_id":306,"parent_id":"9570269467246595","alias":"remont_ustanovka_bytovojj_tekhniki","name":"Ремонт \/ установка бытовой техники","kind":"primary"}],"reviews":{"items":[{"tag":"foursquare","is_reviewable":true}],"org_rating":0,"is_reviewable":false,"org_review_count":0,"is_reviewable_on_flamp":true,"reg_bc_url":"https:\/\/stat.api.2gis.ru\/?v=2.0&hash=78529988G4483123198898G2c6f5c644G6G5G8I2G2I32J1HfEpy397I3378G72003978A271eh2uv08555A22AB38A68357H2G41G2I1di"},"flags":{"photos":false},"external_content":[]},{"id":"70000001018520347_f8579188G4483123198898G2ccd3c644G6G5G8I2G1I33J1HfEpy397I3378G72003978A2712h2uv08555A621579A68357H2G3HG9f","region_id":"68","type":"branch","name":"Absolut, ИП","name_ex":{"primary":"Absolut, ИП"},"point":{"lon":71.435072,"lat":51.10595},"reg_bc_url":"https:\/\/stat.api.2gis.ru\/?v=2.0&hash=48589b88G4483123198898G2cee9c244G6G5G8I2G2I33J1HfEpy397I3378G72003978A2715h2uv08555A621579A68357H2G3H0I2c4","adm_div":[{"id":"9570810633125930","name":"Пригородное пос.","type":"living_area"}],"address":{"components":[{"id":"9571081216076883","type":"street_number","number":"12","street":"Енбекшилер"}],"building_id":"9570784863366788","building_code":"Z05C5X3","reg_bc_url":"https:\/\/stat.api.2gis.ru\/?v=2.0&hash=58559g88G4483123198898G2c692c944G6G5G8I2G2I33J1HfEpy397I3378G72003978A271fh2uv08555A621579A68357H2G44G2I13e"},"address_name":"Енбекшилер, 12","org":{"id":"70000001018520346","name":"Absolut, ИП","branch_count":1},"contact_groups":[{"contacts":[{"type":"phone","value":"+77172456860","text":"+7 (7172) 45‒68‒60","reg_bc_url":"https:\/\/stat.api.2gis.ru\/?v=2.0&hash=485d9388G4483123198898G2cefec344G6G5G8I2G2I33J1HfEpy397I3378G72003978A2718h2uv08555A621579A68357H2G5H0I299"},{"type":"phone","value":"+77072551388","text":"+7‒707‒255‒13‒88","reg_bc_url":"https:\/\/stat.api.2gis.ru\/?v=2.0&hash=38599788G4483123198898G2c84hcc44G6G5G8I2G2I33J1HfEpy397I3378G72003978A2719h2uv08555A621579A68357H2G5H0I227"}]}],"schedule":{"Mon":{"working_hours":[{"to":"21:00","from":"09:00"}]},"Tue":{"working_hours":[{"to":"21:00","from":"09:00"}]},"Wed":{"working_hours":[{"to":"21:00","from":"09:00"}]},"Thu":{"working_hours":[{"to":"21:00","from":"09:00"}]},"Fri":{"working_hours":[{"to":"21:00","from":"09:00"}]},"Sat":{"working_hours":[{"to":"21:00","from":"09:00"}]},"Sun":{"working_hours":[{"to":"21:00","from":"09:00"}]}},"rubrics":[{"id":"9570269467246898","short_id":306,"parent_id":"9570269467246595","alias":"remont_ustanovka_bytovojj_tekhniki","name":"Ремонт \/ установка бытовой техники","kind":"primary"},{"id":"9570269467297458","short_id":50866,"parent_id":"9570269467246602","alias":"vskrytie_obsluzhivanie_zamkov_dverejj","name":"Вскрытие \/ обслуживание замков, дверей","kind":"primary"},{"id":"9570269467269363","short_id":22771,"parent_id":"9570269467246601","alias":"remont_okon","name":"Ремонт окон","kind":"primary"}],"reviews":{"items":[{"tag":"foursquare","is_reviewable":true}],"org_rating":0,"is_reviewable":false,"org_review_count":0,"is_reviewable_on_flamp":true,"reg_bc_url":"https:\/\/stat.api.2gis.ru\/?v=2.0&hash=e8589c88G4483123198898G2c894cd44G6G5G8I2G2I33J1HfEpy397I3378G72003978A271ch2uv08555A621579A68357H2G41G2I176"},"flags":{"photos":false},"external_content":[]},{"id":"70000001023644180_B85b9c88G4483123248898G2c7Bdcb44G6G5G8I2G1I34J1HfEpy397I3378G72003978A2716h2uv08555A7453B2A68357H2G3HG94","region_id":"68","type":"branch","name":"Мастерская по ремонту бытовой техники, ИП Гурьянов А.В.","name_ex":{"primary":"Мастерская по ремонту бытовой техники","extension":"ИП Гурьянов А.В."},"point":{"lon":71.385675,"lat":51.168768},"reg_bc_url":"https:\/\/stat.api.2gis.ru\/?v=2.0&hash=e8589A88G4483123248898G2c645c644G6G5G8I2G2I34J1HfEpy397I3378G72003978A271ch2uv08555A7453B2A68357H2G3H0I25c","adm_div":[],"address":{"components":[{"id":"9571081216070540","type":"street_number","number":"13\/1","street":"Косшыгулулы"}],"building_id":"9570784863339325","building_code":"Z10K1A3","reg_bc_url":"https:\/\/stat.api.2gis.ru\/?v=2.0&hash=e8579388G4483123248898G2c7h6c244G6G5G8I2G2I34J1HfEpy397I3378G72003978A271eh2uv08555A7453B2A68357H2G44G2I1bA"},"address_name":"Косшыгулулы, 13\/1","address_comment":"цокольный этаж; ВП: 2","org":{"id":"70000001023644179","name":"Мастерская по ремонту бытовой техники, ИП Гурьянов А.В.","branch_count":1},"contact_groups":[{"contacts":[{"type":"phone","value":"+77075333243","text":"+7‒707‒533‒32‒43","reg_bc_url":"https:\/\/stat.api.2gis.ru\/?v=2.0&hash=e8579688G4483123248898G2c253c944G6G5G8I2G2I34J1HfEpy397I3378G72003978A271gh2uv08555A7453B2A68357H2G5H0I2bd"},{"type":"phone","value":"+77005333243","text":"+7‒700‒533‒32‒43","reg_bc_url":"https:\/\/stat.api.2gis.ru\/?v=2.0&hash=A85A9488G4483123248898G2cc9Bc244G6G5G8I2G2I34J1HfEpy397I3378G72003978A271gh2uv08555A7453B2A68357H2G5H0I297"}]}],"schedule":{"Mon":{"working_hours":[{"to":"20:00","from":"10:00"}]},"Tue":{"working_hours":[{"to":"20:00","from":"10:00"}]},"Wed":{"working_hours":[{"to":"20:00","from":"10:00"}]},"Thu":{"working_hours":[{"to":"20:00","from":"10:00"}]},"Fri":{"working_hours":[{"to":"20:00","from":"10:00"}]},"Sat":{"working_hours":[{"to":"20:00","from":"10:00"}]}},"rubrics":[{"id":"9570269467246898","short_id":306,"parent_id":"9570269467246595","alias":"remont_ustanovka_bytovojj_tekhniki","name":"Ремонт \/ установка бытовой техники","kind":"primary"},{"id":"9570269467297463","short_id":50871,"parent_id":"9570269467246595","alias":"zapchasti_aksessuary_dlya_bytovojj_tekhniki","name":"Запчасти \/ аксессуары для бытовой техники","kind":"additional"}],"reviews":{"items":[{"tag":"foursquare","is_reviewable":true}],"org_rating":0,"is_reviewable":false,"org_review_count":0,"is_reviewable_on_flamp":true,"reg_bc_url":"https:\/\/stat.api.2gis.ru\/?v=2.0&hash=B85A9c88G4483123248898G2c4h7ce44G6G5G8I2G2I34J1HfEpy397I3378G72003978A271eh2uv08555A7453B2A68357H2G41G2I196"},"flags":{"photos":false},"external_content":[]},{"id":"70000001018511494_485c9d88G4483123198898G2c0e4c644G6G5G8I2G1I35J1HfEpy397I3378G72003978A2716h2uv08555A6126C6A68357H2G3HGg5","region_id":"68","type":"branch","name":"Мади, сервис-центр","name_ex":{"primary":"Мади","extension":"сервис-центр"},"point":{"lon":71.46013,"lat":51.161654},"reg_bc_url":"https:\/\/stat.api.2gis.ru\/?v=2.0&hash=885c9g88G4483123198898G2c756c644G6G5G8I2G2I35J1HfEpy397I3378G72003978A2712h2uv08555A6126C6A68357H2G3H0I265","adm_div":[],"address":{"components":[{"id":"9571081216067264","type":"street_number","number":"10","street":"Жубанова"}],"building_id":"9570784863332218","reg_bc_url":"https:\/\/stat.api.2gis.ru\/?v=2.0&hash=f85e9e88G4483123198898G2c6ABc744G6G5G8I2G2I35J1HfEpy397I3378G72003978A2718h2uv08555A6126C6A68357H2G44G2I1d4"},"address_name":"Жубанова, 10","org":{"id":"70000001018511493","name":"Мади, сервис-центр","branch_count":1},"contact_groups":[{"contacts":[{"type":"phone","value":"+77055983525","text":"+7‒705‒598‒35‒25","reg_bc_url":"https:\/\/stat.api.2gis.ru\/?v=2.0&hash=f8569d88G4483123198898G2c052c644G6G5G8I2G2I35J1HfEpy397I3378G72003978A271Ah2uv08555A6126C6A68357H2G5H0I2g7"},{"type":"phone","value":"+77011454968","text":"+7‒701‒145‒49‒68","reg_bc_url":"https:\/\/stat.api.2gis.ru\/?v=2.0&hash=A8579A88G4483123198898G2c8e4cd44G6G5G8I2G2I35J1HfEpy397I3378G72003978A271ch2uv08555A6126C6A68357H2G5H0I2cg"}]}],"schedule":{"Mon":{"working_hours":[{"to":"18:00","from":"09:00"}]},"Tue":{"working_hours":[{"to":"18:00","from":"09:00"}]},"Wed":{"working_hours":[{"to":"18:00","from":"09:00"}]},"Thu":{"working_hours":[{"to":"18:00","from":"09:00"}]},"Fri":{"working_hours":[{"to":"18:00","from":"09:00"}]},"Sat":{"working_hours":[{"to":"18:00","from":"09:00"}]},"Sun":{"working_hours":[{"to":"18:00","from":"09:00"}]}},"rubrics":[{"id":"9570269467246898","short_id":306,"parent_id":"9570269467246595","alias":"remont_ustanovka_bytovojj_tekhniki","name":"Ремонт \/ установка бытовой техники","kind":"primary"}],"reviews":{"items":[{"tag":"foursquare","is_reviewable":true}],"org_rating":0,"is_reviewable":false,"org_review_count":0,"is_reviewable_on_flamp":true,"reg_bc_url":"https:\/\/stat.api.2gis.ru\/?v=2.0&hash=685b9188G4483123198898G2ce68ce44G6G5G8I2G2I35J1HfEpy397I3378G72003978A2718h2uv08555A6126C6A68357H2G41G2I1e6"},"flags":{"photos":false},"external_content":[]},{"id":"70000001018126887_98529588G4483123198898G2c4BfcA44G6G5G8I2G1I36J1HfEpy397I3378G72003978A2715h2uv08555A227AB9A68357H2G3HG43","region_id":"68","type":"branch","name":"Франкас, сервисная компания","name_ex":{"primary":"Франкас","extension":"сервисная компания"},"point":{"lon":71.464225,"lat":51.167912},"reg_bc_url":"https:\/\/stat.api.2gis.ru\/?v=2.0&hash=d8549288G4483123198898G2c89ece44G6G5G8I2G2I36J1HfEpy397I3378G72003978A271bh2uv08555A227AB9A68357H2G3H0I29f","adm_div":[],"address":{"components":[{"id":"9571081216075339","type":"street_number","number":"23","street":"Жубанова"}],"building_id":"9570784863357247","reg_bc_url":"https:\/\/stat.api.2gis.ru\/?v=2.0&hash=38539288G4483123198898G2c5cccc44G6G5G8I2G2I36J1HfEpy397I3378G72003978A2712h2uv08555A227AB9A68357H2G44G2I1bA"},"address_name":"Жубанова, 23","address_comment":"1 этаж","org":{"id":"70000001018126886","name":"Франкас, сервисная компания","branch_count":1},"contact_groups":[{"contacts":[{"type":"phone","value":"+77781112701","text":"+7‒778‒111‒27‒01","reg_bc_url":"https:\/\/stat.api.2gis.ru\/?v=2.0&hash=985A9f88G4483123198898G2c59fcg44G6G5G8I2G2I36J1HfEpy397I3378G72003978A2716h2uv08555A227AB9A68357H2G5H0I29d"}]}],"schedule":{"Mon":{"working_hours":[{"to":"20:00","from":"09:00"}]},"Tue":{"working_hours":[{"to":"20:00","from":"09:00"}]},"Wed":{"working_hours":[{"to":"20:00","from":"09:00"}]},"Thu":{"working_hours":[{"to":"20:00","from":"09:00"}]},"Fri":{"working_hours":[{"to":"20:00","from":"09:00"}]},"Sat":{"working_hours":[{"to":"20:00","from":"09:00"}]}},"rubrics":[{"id":"9570269467246898","short_id":306,"parent_id":"9570269467246595","alias":"remont_ustanovka_bytovojj_tekhniki","name":"Ремонт \/ установка бытовой техники","kind":"primary"},{"id":"9570269467247242","short_id":650,"parent_id":"9570269467246595","alias":"remont_kompyuterov","name":"Ремонт компьютеров","kind":"primary"}],"reviews":{"items":[{"tag":"foursquare","is_reviewable":true}],"org_rating":0,"is_reviewable":false,"org_review_count":0,"is_reviewable_on_flamp":true,"reg_bc_url":"https:\/\/stat.api.2gis.ru\/?v=2.0&hash=d85c9f88G4483123198898G2c164c944G6G5G8I2G2I36J1HfEpy397I3378G72003978A2712h2uv08555A227AB9A68357H2G41G2I1cf"},"flags":{"photos":false},"external_content":[]},{"id":"70000001018101008_g8599988G4483123198898G2c25ecg44G6G5G8I2G1I37J1HfEpy397I3378G72003978A271gh2uv08555A20223AA68357H2G3HGAg","region_id":"68","type":"branch","name":"Сервисный центр, ИП Континент","name_ex":{"primary":"Сервисный центр","extension":"ИП Континент"},"point":{"lon":71.394343,"lat":51.182964},"reg_bc_url":"https:\/\/stat.api.2gis.ru\/?v=2.0&hash=e85d9588G4483123198898G2cag7c244G6G5G8I2G2I37J1HfEpy397I3378G72003978A271fh2uv08555A20223AA68357H2G3H0I25g","adm_div":[],"address":{"components":[{"id":"9571081216066400","type":"street_number","number":"9\/4","street":"Бекетай"}],"building_id":"9570784863327441","building_code":"Z10M0B1","reg_bc_url":"https:\/\/stat.api.2gis.ru\/?v=2.0&hash=685A9c88G4483123198898G2c423c344G6G5G8I2G2I37J1HfEpy397I3378G72003978A2714h2uv08555A20223AA68357H2G44G2I11f"},"address_name":"Бекетай, 9\/4","address_comment":"вход со двора","org":{"id":"70000001018101007","name":"Сервисный центр, ИП Континент","branch_count":1},"contact_groups":[{"contacts":[{"type":"phone","value":"+77172535204","text":"+7 (7172) 53‒52‒04","reg_bc_url":"https:\/\/stat.api.2gis.ru\/?v=2.0&hash=A85A9988G4483123198898G2c25dc744G6G5G8I2G2I37J1HfEpy397I3378G72003978A271gh2uv08555A20223AA68357H2G5H0I233"},{"type":"phone","value":"+77016459321","text":"+7‒701‒645‒93‒21","reg_bc_url":"https:\/\/stat.api.2gis.ru\/?v=2.0&hash=d8539588G4483123198898G2ce2gcA44G6G5G8I2G2I37J1HfEpy397I3378G72003978A271gh2uv08555A20223AA68357H2G5H0I2f5"},{"type":"phone","value":"+77071632787","text":"+7‒707‒163‒27‒87","reg_bc_url":"https:\/\/stat.api.2gis.ru\/?v=2.0&hash=88559988G4483123198898G2c79fc544G6G5G8I2G2I37J1HfEpy397I3378G72003978A2715h2uv08555A20223AA68357H2G5H0I2b3"}]}],"schedule":{"Mon":{"working_hours":[{"to":"22:00","from":"09:00"}]},"Tue":{"working_hours":[{"to":"22:00","from":"09:00"}]},"Wed":{"working_hours":[{"to":"22:00","from":"09:00"}]},"Thu":{"working_hours":[{"to":"22:00","from":"09:00"}]},"Fri":{"working_hours":[{"to":"22:00","from":"09:00"}]},"Sat":{"working_hours":[{"to":"22:00","from":"09:00"}]},"Sun":{"working_hours":[{"to":"22:00","from":"09:00"}]}},"rubrics":[{"id":"9570269467247220","short_id":628,"parent_id":"9570269467246595","alias":"remont_orgtekhniki","name":"Ремонт оргтехники","kind":"primary"},{"id":"9570269467246898","short_id":306,"parent_id":"9570269467246595","alias":"remont_ustanovka_bytovojj_tekhniki","name":"Ремонт \/ установка бытовой техники","kind":"primary"},{"id":"9570269467247553","short_id":961,"parent_id":"9570269467246595","alias":"remont_audio_video_cifrovojj_tekhniki","name":"Ремонт аудио \/ видео \/ цифровой техники","kind":"primary"}],"reviews":{"items":[{"tag":"foursquare","is_reviewable":true}],"org_rating":0,"is_reviewable":false,"org_review_count":0,"is_reviewable_on_flamp":true,"reg_bc_url":"https:\/\/stat.api.2gis.ru\/?v=2.0&hash=68579888G4483123198898G2c7fecb44G6G5G8I2G2I37J1HfEpy397I3378G72003978A2717h2uv08555A20223AA68357H2G41G2I155"},"flags":{"photos":false},"external_content":[]},{"id":"70000001018514019_i85d9788G4483123198898G2c4dec444G6G5G8I2G1I38J1HfEpy397I3378G72003978A2711h2uv08555A61524BA68357H2G3HGd8","region_id":"68","type":"branch","name":"ТehservisKZ, ИП","name_ex":{"primary":"ТehservisKZ, ИП"},"point":{"lon":71.424767,"lat":51.178418},"reg_bc_url":"https:\/\/stat.api.2gis.ru\/?v=2.0&hash=88539d88G4483123198898G2c47fc444G6G5G8I2G2I38J1HfEpy397I3378G72003978A271Ah2uv08555A61524BA68357H2G3H0I23d","adm_div":[],"address":{"components":[{"id":"9571081216068964","type":"street_number","number":"48\/1","street":"Республики проспект"}],"building_id":"9570784863364727","building_code":"Z10H5D8","reg_bc_url":"https:\/\/stat.api.2gis.ru\/?v=2.0&hash=A85e9f88G4483123198898G2c1c2c744G6G5G8I2G2I38J1HfEpy397I3378G72003978A271bh2uv08555A61524BA68357H2G44G2I167"},"address_name":"Республики проспект, 48\/1","org":{"id":"70000001018514018","name":"ТehservisKZ, ИП","branch_count":1},"contact_groups":[{"contacts":[{"type":"phone","value":"+77075259324","text":"+7‒707‒525‒93‒24","reg_bc_url":"https:\/\/stat.api.2gis.ru\/?v=2.0&hash=88569888G4483123198898G2ceBgce44G6G5G8I2G2I38J1HfEpy397I3378G72003978A2711h2uv08555A61524BA68357H2G5H0I293"},{"type":"phone","value":"+77015259324","text":"+7‒701‒525‒93‒24","reg_bc_url":"https:\/\/stat.api.2gis.ru\/?v=2.0&hash=A8539988G4483123198898G2cfd7c444G6G5G8I2G2I38J1HfEpy397I3378G72003978A2713h2uv08555A61524BA68357H2G5H0I2gb"}]}],"schedule":{"Mon":{"working_hours":[{"to":"21:00","from":"10:00"}]},"Tue":{"working_hours":[{"to":"21:00","from":"10:00"}]},"Wed":{"working_hours":[{"to":"21:00","from":"10:00"}]},"Thu":{"working_hours":[{"to":"21:00","from":"10:00"}]},"Fri":{"working_hours":[{"to":"21:00","from":"10:00"}]},"Sat":{"working_hours":[{"to":"21:00","from":"10:00"}]},"Sun":{"working_hours":[{"to":"21:00","from":"10:00"}]}},"rubrics":[{"id":"9570269467246898","short_id":306,"parent_id":"9570269467246595","alias":"remont_ustanovka_bytovojj_tekhniki","name":"Ремонт \/ установка бытовой техники","kind":"primary"}],"reviews":{"items":[{"tag":"foursquare","is_reviewable":true}],"org_rating":0,"is_reviewable":false,"org_review_count":0,"is_reviewable_on_flamp":true,"reg_bc_url":"https:\/\/stat.api.2gis.ru\/?v=2.0&hash=88539788G4483123198898G2c826c344G6G5G8I2G2I38J1HfEpy397I3378G72003978A2719h2uv08555A61524BA68357H2G41G2I1bg"},"flags":{"photos":false},"external_content":[]},{"id":"70000001021711529_A85f9388G4483123228898G2ceBAc244G6G5G8I2G1I39J1HfEpy397I3378G72003978A271gh2uv08555A81275BA68357H2G3HGAd","region_id":"68","type":"branch","name":"Выездная служба по ремонту холодильников, ИП Rakhila","name_ex":{"primary":"Выездная служба по ремонту холодильников","extension":"ИП Rakhila"},"point":null,"reg_bc_url":"https:\/\/stat.api.2gis.ru\/?v=2.0&hash=f8529188G4483123228898G2ce94cg44G6G5G8I2G2I39J1HfEpy397I3378G72003978A271fh2uv08555A81275BA68357H2G3H0I2fb","adm_div":[],"address":{"components":[{"type":"location","comment":"Астана"}],"reg_bc_url":"https:\/\/stat.api.2gis.ru\/?v=2.0&hash=h8519e88G4483123228898G2ccB7cc44G6G5G8I2G2I39J1HfEpy397I3378G72003978A271gh2uv08555A81275BA68357H2G44G2I1ch"},"org":{"id":"70000001021711528","name":"Выездная служба по ремонту холодильников, ИП Rakhila","branch_count":1},"contact_groups":[{"contacts":[{"type":"phone","value":"+77759405320","text":"+7‒775‒940‒53‒20","reg_bc_url":"https:\/\/stat.api.2gis.ru\/?v=2.0&hash=38579688G4483123228898G2c4Bfcc44G6G5G8I2G2I39J1HfEpy397I3378G72003978A2711h2uv08555A81275BA68357H2G5H0I29e"}]}],"schedule":{"Mon":{"working_hours":[{"to":"24:00","from":"00:00"}]},"Tue":{"working_hours":[{"to":"24:00","from":"00:00"}]},"Wed":{"working_hours":[{"to":"24:00","from":"00:00"}]},"Thu":{"working_hours":[{"to":"24:00","from":"00:00"}]},"Fri":{"working_hours":[{"to":"24:00","from":"00:00"}]},"Sat":{"working_hours":[{"to":"24:00","from":"00:00"}]},"Sun":{"working_hours":[{"to":"24:00","from":"00:00"}]}},"rubrics":[{"id":"9570269467246898","short_id":306,"parent_id":"9570269467246595","alias":"remont_ustanovka_bytovojj_tekhniki","name":"Ремонт \/ установка бытовой техники","kind":"primary"}],"reviews":{"items":[{"tag":"foursquare","is_reviewable":true}],"org_rating":0,"is_reviewable":false,"org_review_count":0,"is_reviewable_on_flamp":true,"reg_bc_url":"https:\/\/stat.api.2gis.ru\/?v=2.0&hash=B85g9488G4483123228898G2c2cdc544G6G5G8I2G2I39J1HfEpy397I3378G72003978A2717h2uv08555A81275BA68357H2G41G2I153"},"flags":{"photos":false},"external_content":[]},{"id":"70000001018086972_f85c9e88G4483123198898G2c19cc444G6G5G8I2G1I40J1HfEpy397I3378G72003978A271Ah2uv08555A187BA4A68357H2G3HGd5","region_id":"68","type":"branch","name":"Многопрофильная компания, ИП Кузнецов М.А.","name_ex":{"primary":"Многопрофильная компания","extension":"ИП Кузнецов М.А."},"point":{"lon":71.412769,"lat":51.17696},"reg_bc_url":"https:\/\/stat.api.2gis.ru\/?v=2.0&hash=C85g9588G4483123198898G2c85cc244G6G5G8I2G2I40J1HfEpy397I3378G72003978A2716h2uv08555A187BA4A68357H2G3H0I243","adm_div":[],"address":{"components":[{"id":"9571081216068438","type":"street_number","number":"37","street":"Желтоксан"}],"building_id":"9570784863341424","building_code":"Z10M9X2","reg_bc_url":"https:\/\/stat.api.2gis.ru\/?v=2.0&hash=785f9288G4483123198898G2c67Bc444G6G5G8I2G2I40J1HfEpy397I3378G72003978A271eh2uv08555A187BA4A68357H2G44G2I15B"},"address_name":"Желтоксан, 37","address_comment":"5 этаж","org":{"id":"70000001018086971","name":"Многопрофильная компания, ИП Кузнецов М.А.","branch_count":1},"contact_groups":[{"contacts":[{"type":"phone","value":"+77016275696","text":"+7‒701‒627‒56‒96","reg_bc_url":"https:\/\/stat.api.2gis.ru\/?v=2.0&hash=B8579288G4483123198898G2cfgecf44G6G5G8I2G2I40J1HfEpy397I3378G72003978A271gh2uv08555A187BA4A68357H2G5H0I2A3"},{"type":"phone","value":"+77021813397","text":"+7‒702‒181‒33‒97","reg_bc_url":"https:\/\/stat.api.2gis.ru\/?v=2.0&hash=68569e88G4483123198898G2cd63c944G6G5G8I2G2I40J1HfEpy397I3378G72003978A2718h2uv08555A187BA4A68357H2G5H0I286"},{"type":"phone","value":"+77021813403","text":"+7‒702‒181‒34‒03","reg_bc_url":"https:\/\/stat.api.2gis.ru\/?v=2.0&hash=58519d88G4483123198898G2cb82c244G6G5G8I2G2I40J1HfEpy397I3378G72003978A2716h2uv08555A187BA4A68357H2G5H0I22e"}]}],"schedule":{"Mon":{"working_hours":[{"to":"24:00","from":"08:00"}]},"Tue":{"working_hours":[{"to":"24:00","from":"08:00"}]},"Wed":{"working_hours":[{"to":"24:00","from":"08:00"}]},"Thu":{"working_hours":[{"to":"24:00","from":"08:00"}]},"Fri":{"working_hours":[{"to":"24:00","from":"08:00"}]},"Sat":{"working_hours":[{"to":"24:00","from":"08:00"}]},"Sun":{"working_hours":[{"to":"24:00","from":"08:00"}]}},"rubrics":[{"id":"9570269467246871","short_id":279,"parent_id":"9570269467246601","alias":"ehlektromontazhnye_raboty","name":"Электромонтажные работы","kind":"primary"},{"id":"9570269467246898","short_id":306,"parent_id":"9570269467246595","alias":"remont_ustanovka_bytovojj_tekhniki","name":"Ремонт \/ установка бытовой техники","kind":"primary"}],"reviews":{"items":[{"tag":"foursquare","is_reviewable":true}],"org_rating":0,"is_reviewable":false,"org_review_count":0,"is_reviewable_on_flamp":true,"reg_bc_url":"https:\/\/stat.api.2gis.ru\/?v=2.0&hash=h8529688G4483123198898G2cb36cc44G6G5G8I2G2I40J1HfEpy397I3378G72003978A271Ah2uv08555A187BA4A68357H2G41G2I187"},"flags":{"photos":false},"external_content":[]},{"id":"70000001023603440_98599388G4483123248898G2c799c344G6G5G8I2G1I41J1HfEpy397I3378G72003978A2711h2uv08555A704672A68357H2G3HGe9","region_id":"68","type":"branch","name":"Мастерская по ремонту холодильного оборудования и автокондиционеров","name_ex":{"primary":"Мастерская по ремонту холодильного оборудования и автокондиционеров"},"point":{"lon":71.448535,"lat":51.157018},"reg_bc_url":"https:\/\/stat.api.2gis.ru\/?v=2.0&hash=C85f9588G4483123248898G2c369cf44G6G5G8I2G2I41J1HfEpy397I3378G72003978A271gh2uv08555A704672A68357H2G3H0I2f5","adm_div":[{"id":"9570810633125931","name":"Целинный м-н","type":"living_area"}],"address":{"components":[{"id":"9571081216067153","type":"street_number","number":"14а","street":"Кравцова"}],"building_id":"9570784863337072","reg_bc_url":"https:\/\/stat.api.2gis.ru\/?v=2.0&hash=f85f9588G4483123248898G2cfg4c444G6G5G8I2G2I41J1HfEpy397I3378G72003978A2715h2uv08555A704672A68357H2G44G2I1c4"},"address_name":"Кравцова, 14а","org":{"id":"70000001023603439","name":"Мастерская по ремонту холодильного оборудования и автокондиционеров","branch_count":1},"contact_groups":[{"contacts":[{"type":"phone","value":"+77752776557","text":"+7‒775‒277‒65‒57","reg_bc_url":"https:\/\/stat.api.2gis.ru\/?v=2.0&hash=585A9b88G4483123248898G2ccdccd44G6G5G8I2G2I41J1HfEpy397I3378G72003978A2717h2uv08555A704672A68357H2G5H0I285"}]}],"schedule":{"Mon":{"working_hours":[{"to":"18:00","from":"09:00"}]},"Tue":{"working_hours":[{"to":"18:00","from":"09:00"}]},"Wed":{"working_hours":[{"to":"18:00","from":"09:00"}]},"Thu":{"working_hours":[{"to":"18:00","from":"09:00"}]},"Fri":{"working_hours":[{"to":"18:00","from":"09:00"}]},"Sat":{"working_hours":[{"to":"18:00","from":"09:00"}]},"Sun":{"working_hours":[{"to":"18:00","from":"09:00"}]}},"rubrics":[{"id":"9570269467254289","short_id":7697,"parent_id":"9570269467289495","alias":"remont_zapravka_avtokondicionerov","name":"Ремонт \/ заправка автокондиционеров","kind":"primary"},{"id":"9570269467246898","short_id":306,"parent_id":"9570269467246595","alias":"remont_ustanovka_bytovojj_tekhniki","name":"Ремонт \/ установка бытовой техники","kind":"primary"},{"id":"9570269467303832","short_id":57240,"parent_id":"9570269467246607","alias":"remont_torgovogo_oborudovaniya","name":"Ремонт торгового оборудования","kind":"primary"}],"reviews":{"items":[{"tag":"foursquare","is_reviewable":true}],"org_rating":0,"is_reviewable":false,"org_review_count":0,"is_reviewable_on_flamp":true,"reg_bc_url":"https:\/\/stat.api.2gis.ru\/?v=2.0&hash=i8519e88G4483123248898G2c086cA44G6G5G8I2G2I41J1HfEpy397I3378G72003978A2715h2uv08555A704672A68357H2G41G2I155"},"flags":{"photos":false},"external_content":[]},{"id":"70000001018510351_48559d88G4483123198898G2cde7c844G6G5G8I2G1I42J1HfEpy397I3378G72003978A2711h2uv08555A611583A68357H2G3HG92","region_id":"68","type":"branch","name":"Выездная служба ремонта, ИП Жильцов М.В.","name_ex":{"primary":"Выездная служба ремонта","extension":"ИП Жильцов М.В."},"point":null,"reg_bc_url":"https:\/\/stat.api.2gis.ru\/?v=2.0&hash=h85g9A88G4483123198898G2c0cBc744G6G5G8I2G2I42J1HfEpy397I3378G72003978A2713h2uv08555A611583A68357H2G3H0I2Ac","adm_div":[],"address":{"components":[{"type":"location","comment":"Астана"}],"reg_bc_url":"https:\/\/stat.api.2gis.ru\/?v=2.0&hash=88549788G4483123198898G2cf87c844G6G5G8I2G2I42J1HfEpy397I3378G72003978A2719h2uv08555A611583A68357H2G44G2I1e8"},"org":{"id":"70000001018510350","name":"Выездная служба ремонта, ИП Жильцов М.В.","branch_count":1},"contact_groups":[{"contacts":[{"type":"phone","value":"+77021685268","text":"+7‒702‒168‒52‒68","reg_bc_url":"https:\/\/stat.api.2gis.ru\/?v=2.0&hash=B8589f88G4483123198898G2cc22c944G6G5G8I2G2I42J1HfEpy397I3378G72003978A2714h2uv08555A611583A68357H2G5H0I224"},{"type":"phone","value":"+77172564065","text":"+7 (7172) 56‒40‒65","reg_bc_url":"https:\/\/stat.api.2gis.ru\/?v=2.0&hash=h8529888G4483123198898G2c627cA44G6G5G8I2G2I42J1HfEpy397I3378G72003978A271gh2uv08555A611583A68357H2G5H0I22d"}]}],"schedule":{"Mon":{"working_hours":[{"to":"20:00","from":"08:00"}]},"Tue":{"working_hours":[{"to":"20:00","from":"08:00"}]},"Wed":{"working_hours":[{"to":"20:00","from":"08:00"}]},"Thu":{"working_hours":[{"to":"20:00","from":"08:00"}]},"Fri":{"working_hours":[{"to":"20:00","from":"08:00"}]},"Sat":{"working_hours":[{"to":"20:00","from":"08:00"}]},"Sun":{"working_hours":[{"to":"20:00","from":"08:00"}]}},"rubrics":[{"id":"9570269467246898","short_id":306,"parent_id":"9570269467246595","alias":"remont_ustanovka_bytovojj_tekhniki","name":"Ремонт \/ установка бытовой техники","kind":"primary"},{"id":"9570269467271404","short_id":24812,"parent_id":"9570269467246607","alias":"remont_obsluzhivanie_klimaticheskogo_oborudovaniya","name":"Ремонт \/ обслуживание климатического оборудования","kind":"primary"}],"reviews":{"items":[{"tag":"foursquare","is_reviewable":true}],"org_rating":0,"is_reviewable":false,"org_review_count":0,"is_reviewable_on_flamp":true,"reg_bc_url":"https:\/\/stat.api.2gis.ru\/?v=2.0&hash=g8599f88G4483123198898G2c98BcA44G6G5G8I2G2I42J1HfEpy397I3378G72003978A2717h2uv08555A611583A68357H2G41G2I1Ah"},"flags":{"photos":false},"external_content":[]}],"filters":{"attributes":[{"label":"Наличный расчет","tag":"general_payment_type_cash","type":"flag"},{"label":"Visa","tag":"general_payment_type_visa","type":"flag"},{"label":"MasterCard","tag":"general_payment_type_mastercard","type":"flag"},{"label":"Оплата через банк","tag":"general_payment_type_noncash","type":"flag"},{"label":"Оплата через Интернет","tag":"general_payment_type_internet","type":"flag"}],"rubrics":[{"name":"Ремонт \/ установка бытовой техники","id":"9570269467246898","count":33},{"name":"Электромонтажные работы","id":"9570269467246871","count":2},{"name":"Ремонт \/ обслуживание климатического оборудования","id":"9570269467271404","count":4},{"name":"Ремонт компьютеров","id":"9570269467247242","count":7},{"name":"Ремонт аудио \/ видео \/ цифровой техники","id":"9570269467247553","count":4},{"name":"Ремонт \/ установка сантехнического оборудования","id":"9570269467350789","count":2},{"name":"Ремонт \/ отделка помещений","id":"9570269467246868","count":1},{"name":"Ремонт оргтехники","id":"9570269467247220","count":3},{"name":"Ремонт промышленного оборудования","id":"9570269467252247","count":3},{"name":"Запчасти \/ аксессуары для бытовой техники","id":"9570269467297463","count":2},{"name":"Выездная техническая помощь на дороге","id":"9570269467356908","count":1},{"name":"Вскрытие \/ обслуживание замков, дверей","id":"9570269467297458","count":2},{"name":"Профессиональная уборка","id":"9570269467247301","count":1},{"name":"Ремонт окон","id":"9570269467269363","count":1},{"name":"Ремонт мобильных устройств связи","id":"9570269467247259","count":1},{"name":"Заправка картриджей","id":"9570269467251010","count":1},{"name":"Ремонт \/ заправка автокондиционеров","id":"9570269467254289","count":1},{"name":"Ремонт торгового оборудования","id":"9570269467303832","count":1}],"spatial":{"cities":[{"name":"Астана","id":"9570771978420226","count":33}],"districts":[{"name":"Район \"Алматы\"","id":"9570759093518343","city_id":"9570771978420226"},{"name":"Район \"Сарыарка\"","id":"9570759093518341","city_id":"9570771978420226"},{"name":null,"id":"","city_id":"9570771978420226"},{"name":"Район \"Есиль\"","id":"9570759093518340","city_id":"9570771978420226"}]}},"widgets":{"main":[{"labels":{"fri":"Пт","mon":"Пн","now":"Открыто сейчас","sat":"Сб","sun":"ВС","thu":"Чт","tue":"Вт","wed":"Ср","alltime":"Круглосуточно","specified":"В указанное время"},"widget":"worktime","time_format":"24h","first_week_day":"mon"},{"items":[[{"text":"Есть сайт","type":"filter","values":["has_site"]},{"text":"Есть фото","type":"filter","values":["has_photos"]}],[{"text":"Расчёт по картам","type":"filter","values":["general_payment_type_visa","general_payment_type_mastercard"]}]],"widget":"checkboxlist","expanding":[]}],"actions":[{"items":[[{"text":"Открыто","type":"filter","values":["work_time_now"]},{"text":"На карте","type":"filter","values":["bound"]}]],"widget":"checkboxlist","expanding":[]}]},"request_type":"discovery","context_rubrics":[{"id":"9570269467246898","short_id":306,"name":"Ремонт \/ установка бытовой техники"}],"search_attributes":{"context_rubrics":["9570269467246898"],"advertisers":[{"org":"70000001018096447","rubr":"9570269467246898"}]}}}